Workbook
Name ListaInsumos: Insumos!$A:$A
Name Todos_Produtos: LISTAS!$G$2:$G$69
Name Categorias: LISTAS!$I$2:$I$6

Sheet UNIFICADO
A1: TOCS BURGER — Fichas Técnicas Unificadas
A3: Categoria | B3: Produto | C3: CMV | D3: Preço Site | E3: Preço Loja | F3: Preço iFood | G3: CMV Site | H3: CMV IFOOD | I3: CMV LOJA
A4: Lanche | B4: Priscilo | C4: =IFERROR(VLOOKUP(B4,'COMPARAÇÃO DE PREÇOS'!A:E,2,FALSE),"") -> 4.9151065 | D4: =IFERROR(VLOOKUP(B4,'COMPARAÇÃO DE PREÇOS'!A:E,3,FALSE),"") -> 35 | E4: =IFERROR(VLOOKUP(B4,'COMPARAÇÃO DE PREÇOS'!A:E,5,FALSE),"") -> 35 | F4: =IFERROR(VLOOKUP(B4,'COMPARAÇÃO DE PREÇOS'!A:E,4,FALSE),"") -> 41.7 | G4: =IF(OR(C4="",D4=""),"",C4/D4) -> 0.14043161 | H4: =IF(OR(C4="",E4=""),"",C4/E4) -> 0.14043161 | I4: =IF(OR(C4="",F4=""),"",C4/F4) -> 0.11786826
A5: Porção | B5: Batata P | C5: =IFERROR(VLOOKUP(B5,'COMPARAÇÃO DE PREÇOS'!A:E,2,FALSE),"") -> 3.2723077 | D5: =IFERROR(VLOOKUP(B5,'COMPARAÇÃO DE PREÇOS'!A:E,3,FALSE),"") -> 20 | E5: =IFERROR(VLOOKUP(B5,'COMPARAÇÃO DE PREÇOS'!A:E,5,FALSE),"") -> 20 | F5: =IFERROR(VLOOKUP(B5,'COMPARAÇÃO DE PREÇOS'!A:E,4,FALSE),"") -> 24.9 | G5: =IF(OR(C5="",D5=""),"",C5/D5) -> 0.16361538 | H5: =IF(OR(C5="",E5=""),"",C5/E5) -> 0.16361538 | I5: =IF(OR(C5="",F5=""),"",C5/F5) -> 0.13141798
A6: Porção | B6: Onion Rings P | C6: =IFERROR(VLOOKUP(B6,'COMPARAÇÃO DE PREÇOS'!A:E,2,FALSE),"") -> 3.296 | D6: =IFERROR(VLOOKUP(B6,'COMPARAÇÃO DE PREÇOS'!A:E,3,FALSE),"") -> 20 | E6: =IFERROR(VLOOKUP(B6,'COMPARAÇÃO DE PREÇOS'!A:E,5,FALSE),"") -> 20 | F6: =IFERROR(VLOOKUP(B6,'COMPARAÇÃO DE PREÇOS'!A:E,4,FALSE),"") -> 24.9 | G6: =IF(OR(C6="",D6=""),"",C6/D6) -> 0.1648 | H6: =IF(OR(C6="",E6=""),"",C6/E6) -> 0.1648 | I6: =IF(OR(C6="",F6=""),"",C6/F6) -> 0.13236948
A7: Lanche | B7: Albieri | C7: =IFERROR(VLOOKUP(B7,'COMPARAÇÃO DE PREÇOS'!A:E,2,FALSE),"") -> 8.94527 | D7: =IFERROR(VLOOKUP(B7,'COMPARAÇÃO DE PREÇOS'!A:E,3,FALSE),"") -> 43 | E7: =IFERROR(VLOOKUP(B7,'COMPARAÇÃO DE PREÇOS'!A:E,5,FALSE),"") -> 43 | F7: =IFERROR(VLOOKUP(B7,'COMPARAÇÃO DE PREÇOS'!A:E,4,FALSE),"") -> 51.9 | G7: =IF(OR(C7="",D7=""),"",C7/D7) -> 0.20802953 | H7: =IF(OR(C7="",E7=""),"",C7/E7) -> 0.20802953 | I7: =IF(OR(C7="",F7=""),"",C7/F7) -> 0.17235588
A8: Porção | B8: Onion Rings M | C8: =IFERROR(VLOOKUP(B8,'COMPARAÇÃO DE PREÇOS'!A:E,2,FALSE),"") -> 4.484 | D8: =IFERROR(VLOOKUP(B8,'COMPARAÇÃO DE PREÇOS'!A:E,3,FALSE),"") -> 25 | E8: =IFERROR(VLOOKUP(B8,'COMPARAÇÃO DE PREÇOS'!A:E,5,FALSE),"") -> 25 | F8: =IFERROR(VLOOKUP(B8,'COMPARAÇÃO DE PREÇOS'!A:E,4,FALSE),"") -> 31.9 | G8: =IF(OR(C8="",D8=""),"",C8/D8) -> 0.17936 | H8: =IF(OR(C8="",E8=""),"",C8/E8) -> 0.17936 | I8: =IF(OR(C8="",F8=""),"",C8/F8) -> 0.14056426
A9: Porção | B9: Onion Rings G | C9: =IFERROR(VLOOKUP(B9,'COMPARAÇÃO DE PREÇOS'!A:E,2,FALSE),"") -> 6.86 | D9: =IFERROR(VLOOKUP(B9,'COMPARAÇÃO DE PREÇOS'!A:E,3,FALSE),"") -> 35 | E9: =IFERROR(VLOOKUP(B9,'COMPARAÇÃO DE PREÇOS'!A:E,5,FALSE),"") -> 35 | F9: =IFERROR(VLOOKUP(B9,'COMPARAÇÃO DE PREÇOS'!A:E,4,FALSE),"") -> 37.7 | G9: =IF(OR(C9="",D9=""),"",C9/D9) -> 0.196 | H9: =IF(OR(C9="",E9=""),"",C9/E9) -> 0.196 | I9: =IF(OR(C9="",F9=""),"",C9/F9) -> 0.18196286
A10: Lanche | B10: Simples | C10: =IFERROR(VLOOKUP(B10,'COMPARAÇÃO DE PREÇOS'!A:E,2,FALSE),"") -> 4.6137105 | D10: =IFERROR(VLOOKUP(B10,'COMPARAÇÃO DE PREÇOS'!A:E,3,FALSE),"") -> 23 | E10: =IFERROR(VLOOKUP(B10,'COMPARAÇÃO DE PREÇOS'!A:E,5,FALSE),"") -> 23 | F10: =IFERROR(VLOOKUP(B10,'COMPARAÇÃO DE PREÇOS'!A:E,4,FALSE),"") -> 34 | G10: =IF(OR(C10="",D10=""),"",C10/D10) -> 0.20059611 | H10: =IF(OR(C10="",E10=""),"",C10/E10) -> 0.20059611 | I10: =IF(OR(C10="",F10=""),"",C10/F10) -> 0.13569737
A11: Lanche | B11: Osvaldão | C11: =IFERROR(VLOOKUP(B11,'COMPARAÇÃO DE PREÇOS'!A:E,2,FALSE),"") -> 11.397056 | D11: =IFERROR(VLOOKUP(B11,'COMPARAÇÃO DE PREÇOS'!A:E,3,FALSE),"") -> 39 | E11: =IFERROR(VLOOKUP(B11,'COMPARAÇÃO DE PREÇOS'!A:E,5,FALSE),"") -> 39 | F11: =IFERROR(VLOOKUP(B11,'COMPARAÇÃO DE PREÇOS'!A:E,4,FALSE),"") -> 51.9 | G11: =IF(OR(C11="",D11=""),"",C11/D11) -> 0.2922322 | H11: =IF(OR(C11="",E11=""),"",C11/E11) -> 0.2922322 | I11: =IF(OR(C11="",F11=""),"",C11/F11) -> 0.21959645
A12: Porção | B12: Porção Mista | C12: =IFERROR(VLOOKUP(B12,'COMPARAÇÃO DE PREÇOS'!A:E,2,FALSE),"") -> 9.3600092 | D12: =IFERROR(VLOOKUP(B12,'COMPARAÇÃO DE PREÇOS'!A:E,3,FALSE),"") -> 45 | E12: =IFERROR(VLOOKUP(B12,'COMPARAÇÃO DE PREÇOS'!A:E,5,FALSE),"") -> 45 | F12: =IFERROR(VLOOKUP(B12,'COMPARAÇÃO DE PREÇOS'!A:E,4,FALSE),"") -> 55 | G12: =IF(OR(C12="",D12=""),"",C12/D12) -> 0.20800021 | H12: =IF(OR(C12="",E12=""),"",C12/E12) -> 0.20800021 | I12: =IF(OR(C12="",F12=""),"",C12/F12) -> 0.17018199
A13: Bebida | B13: Água Sem Gás | C13: =IFERROR(VLOOKUP(B13,'COMPARAÇÃO DE PREÇOS'!A:E,2,FALSE),"") -> 1.0675 | D13: =IFERROR(VLOOKUP(B13,'COMPARAÇÃO DE PREÇOS'!A:E,3,FALSE),"") -> 5 | E13: =IFERROR(VLOOKUP(B13,'COMPARAÇÃO DE PREÇOS'!A:E,5,FALSE),"") -> 5 | F13: =IFERROR(VLOOKUP(B13,'COMPARAÇÃO DE PREÇOS'!A:E,4,FALSE),"") -> 6 | G13: =IF(OR(C13="",D13=""),"",C13/D13) -> 0.2135 | H13: =IF(OR(C13="",E13=""),"",C13/E13) -> 0.2135 | I13: =IF(OR(C13="",F13=""),"",C13/F13) -> 0.17791667
A14: Porção | B14: Batata M | C14: =IFERROR(VLOOKUP(B14,'COMPARAÇÃO DE PREÇOS'!A:E,2,FALSE),"") -> 5.6246154 | D14: =IFERROR(VLOOKUP(B14,'COMPARAÇÃO DE PREÇOS'!A:E,3,FALSE),"") -> 25 | E14: =IFERROR(VLOOKUP(B14,'COMPARAÇÃO DE PREÇOS'!A:E,5,FALSE),"") -> 25 | F14: =IFERROR(VLOOKUP(B14,'COMPARAÇÃO DE PREÇOS'!A:E,4,FALSE),"") -> 31.9 | G14: =IF(OR(C14="",D14=""),"",C14/D14) -> 0.22498462 | H14: =IF(OR(C14="",E14=""),"",C14/E14) -> 0.22498462 | I14: =IF(OR(C14="",F14=""),"",C14/F14) -> 0.17632023
A15: Porção | B15: Nuggets P | C15: =IFERROR(VLOOKUP(B15,'COMPARAÇÃO DE PREÇOS'!A:E,2,FALSE),"") -> 4.6317015 | D15: =IFERROR(VLOOKUP(B15,'COMPARAÇÃO DE PREÇOS'!A:E,3,FALSE),"") -> 20 | E15: =IFERROR(VLOOKUP(B15,'COMPARAÇÃO DE PREÇOS'!A:E,5,FALSE),"") -> 20 | F15: =IFERROR(VLOOKUP(B15,'COMPARAÇÃO DE PREÇOS'!A:E,4,FALSE),"") -> 24.9 | G15: =IF(OR(C15="",D15=""),"",C15/D15) -> 0.23158508 | H15: =IF(OR(C15="",E15=""),"",C15/E15) -> 0.23158508 | I15: =IF(OR(C15="",F15=""),"",C15/F15) -> 0.18601211
... A79: Adicionais | B79: Cebola Caramelizada | C79: =IFERROR(VLOOKUP(B79,'COMPARAÇÃO DE PREÇOS'!A:E,2,FALSE),"") | D79: =IFERROR(VLOOKUP(B79,'COMPARAÇÃO DE PREÇOS'!A:E,3,FALSE),"") | E79: =IFERROR(VLOOKUP(B79,'COMPARAÇÃO DE PREÇOS'!A:E,5,FALSE),"") | F79: =IFERROR(VLOOKUP(B79,'COMPARAÇÃO DE PREÇOS'!A:E,4,FALSE),"") | G79: =IF(OR(C79="",D79=""),"",C79/D79) | H79: =IF(OR(C79="",E79=""),"",C79/E79) | I79: =IF(OR(C79="",F79=""),"",C79/F79)

Sheet Insumos
B1: Unidade | C1: Valor | D1: Fator de Conversão | E1: Valor Unitário
A2: Açucar KG | B2: KG | C2: 4.99 | D2: 1000 | E2: =C2/D2 -> 0.00499
A3: Água | B3: L | C3: 1 | D3: 1000 | E3: =C3/D3 -> 0.001
A4: Alcaparras | B4: KG | C4: 12 | D4: 200 | E4: =C4/D4 -> 0.06
A5: Alface KG | B5: KG | C5: 24.1 | D5: 1000 | E5: =C5/D5 -> 0.0241
A6: Alho KG | B6: KG | C6: 29.99 | D6: 1000 | E6: =C6/D6 -> 0.02999
A7: Amido de Milho KG | B7: KG | C7: 7.29 | D7: 1000 | E7: =C7/D7 -> 0.00729
A8: Bacon Fatiado KG | B8: KG | C8: 43 | D8: 1000 | E8: =C8/D8 -> 0.043
A9: Batata Congelada KG | B9: KG | C9: 15.29 | D9: 1000 | E9: =C9/D9 -> 0.01529
A10: Caixa de Fritura G | B10: UN | C10: 5160 | D10: 6000 | E10: =C10/D10 -> 0.86
A11: Caixa de Fritura P | B11: UN | C11: 5160 | D11: 6000 | E11: =C11/D11 -> 0.86
A12: Carne Moída KG | B12: KG | C12: 24.99 | D12: 1000 | E12: =C12/D12 -> 0.02499
A13: Cebola Branca KG | B13: KG | C13: 2 | D13: 1000 | E13: =C13/D13 -> 0.002
... A42: Tomate KG | B42: KG | C42: 6 | D42: 1000 | E42: =C42/D42 -> 0.006
A43: Cebola Branca Limpa | B43: KG | C43: =VLOOKUP(A43,Preparos!A:E,3,FALSE) -> 2.5 | D43: 1000 | E43: =C43/D43 -> 0.0025
A44: Papel Acoplado | B44: UN | C44: 5120 | D44: 40000 | E44: =C44/D44 -> 0.128
A45: Barbecue KG | B45: KG | C45: 49.9 | D45: 2000 | E45: =C45/D45 -> 0.02495
A46: Churros Recheados KG | B46: KG | C46: 30 | D46: 1000 | E46: =C46/D46 -> 0.03
A47: Churros Palito KG | B47: KG | C47: 30 | D47: 1000 | E47: =C47/D47 -> 0.03
A48: Sorvete KG | B48: KG | C48: 84 | D48: 1000 | E48: =C48/D48 -> 0.084
A49: Calda de Chocolate KG | B49: KG | C49: 648.9 | D49: 15000 | E49: =C49/D49 -> 0.04326
A50: Brownie Lhamaria | B50: UN | C50: 6.5 | D50: 1 | E50: =C50/D50 -> 6.5
A51: Cookie Lhamaria | B51: UN | C51: 6.5 | D51: 1 | E51: =C51/D51 -> 6.5
A52: Linguiça | B52: KG | C52: 18 | D52: 1000 | E52: =C52/D52 -> 0.018
A53: Abacaxi KG | B53: KG | C53: 15.8 | D53: 400 | E53: =C53/D53 -> 0.0395
A54: Disco de frango | B54: UN
A56: PREPARADOS | E56: =IF(D54="","",C54/D54)
A57: Pasta de Cebola Roxa | B57: KG | C57: =VLOOKUP(A57,Preparos!A:E,3,FALSE) -> 5.7482759 | D57: =VLOOKUP(A57,Preparos!A:E,2,FALSE) -> 600 | E57: =IF(D57="","",C57/D57) -> 0.0095804598
A58: Bacon Frito | B58: KG | C58: =VLOOKUP(A58,Preparos!A:E,3,FALSE) -> 43 | D58: =VLOOKUP(A58,Preparos!A:E,2,FALSE) -> 296 | E58: =IF(D58="","",C58/D58) -> 0.14527027
A59: Mirocley | B59: KG | C59: =VLOOKUP(A59,Preparos!A:E,3,FALSE) -> 122.22723 | D59: =VLOOKUP(A59,Preparos!A:E,2,FALSE) -> 8000 | E59: =IF(D59="","",C59/D59) -> 0.015278403
A60: Molho do Frango | B60: KG | C60: =VLOOKUP(A60,Preparos!A:E,3,FALSE) -> 87.558707 | D60: =VLOOKUP(A60,Preparos!A:E,2,FALSE) -> 4895 | E60: =IF(D60="","",C60/D60) -> 0.017887376
A61: Bacon Dose | B61: KG | C61: =VLOOKUP(A61,Preparos!A:E,3,FALSE) -> 2.9054054 | D61: =VLOOKUP(A61,Preparos!A:E,2,FALSE) -> 1 | E61: =IF(D61="","",C61/D61) -> 2.9054054
A62: Bacon Batatas | B62: KG | C62: =VLOOKUP(A62,Preparos!A:E,3,FALSE) -> 4.3581081 | D62: =VLOOKUP(A62,Preparos!A:E,2,FALSE) -> 1 | E62: =IF(D62="","",C62/D62) -> 4.3581081
A63: Mussarela Fatia | B63: UN | C63: =VLOOKUP(A63,Preparos!A:E,3,FALSE) -> 0.6798 | D63: =VLOOKUP(A63,Preparos!A:E,2,FALSE) -> 1 | E63: =IF(D63="","",C63/D63) -> 0.6798
A64: Cheddar Fatia | B64: UN | C64: =VLOOKUP(A64,Preparos!A:E,3,FALSE) -> 0.50386 | D64: =VLOOKUP(A64,Preparos!A:E,2,FALSE) -> 1 | E64: =IF(D64="","",C64/D64) -> 0.50386
A65: Batata Frita 100g | B65: UN | C65: =VLOOKUP(A65,Preparos!A:E,3,FALSE) -> 2.3523077 | D65: =VLOOKUP(A65,Preparos!A:E,2,FALSE) -> 1 | E65: =IF(D65="","",C65/D65) -> 2.3523077
A66: Onion Ring Un. | B66: UN | C66: =VLOOKUP(A66,Preparos!A:E,3,FALSE) -> 0.297 | D66: =VLOOKUP(A66,Preparos!A:E,2,FALSE) -> 1 | E66: =IF(D66="","",C66/D66) -> 0.297
A67: Nuggets Un. | B67: UN | C67: =VLOOKUP(A67,Preparos!A:E,3,FALSE) -> 0.46396269 | D67: =VLOOKUP(A67,Preparos!A:E,2,FALSE) -> 1 | E67: =IF(D67="","",C67/D67) -> 0.46396269
A68: Smash Burger | B68: UN | C68: =VLOOKUP(A68,Preparos!A:E,3,FALSE) -> 1.9992 | D68: =VLOOKUP(A68,Preparos!A:E,2,FALSE) -> 1 | E68: =IF(D68="","",C68/D68) -> 1.9992
... A84: Smash Linguiça | B84: KG | C84: =VLOOKUP(A84,Preparos!A:E,3,FALSE) -> 1.44 | D84: =VLOOKUP(A84,Preparos!A:E,2,FALSE) -> 1 | E84: =IF(D84="","",C84/D84) -> 1.44
E86: =IF(D85="","",C85/D85)
E87: =IF(D86="","",C86/D86)
E88: =IF(D87="","",C87/D87)
E89: =IF(D88="","",C88/D88)
E90: =IF(D89="","",C89/D89)
E91: =IF(D90="","",C90/D90)
E92: =IF(D91="","",C91/D91)
E93: =IF(D92="","",C92/D92)
E94: =IF(D93="","",C93/D93)
E95: =IF(D94="","",C94/D94)
E96: =IF(D95="","",C95/D95)
E97: =IF(D96="","",C96/D96)
... E145: =IF(D144="","",C144/D144)

Sheet Preparos
B1: Gramas | C1: Valor | D1: Valor Unitário
A2: Cebola Branca Limpa | B2: 1000 | C2: =C3 -> 2.5 | D2: =C2/B2 -> 0.0025
A3: Cebola Branca KG | B3: 1250 | C3: =VLOOKUP(A3,Insumos!A:E,5,FALSE)*B3 -> 2.5
A6: Cebola Caramelizada | B6: 1387 | C6: =SUM(C7:C11) -> 13.89345 | D6: =C6/B6 -> 0.010016907
A7: Cebola Branca Limpa | B7: 1000 | C7: =VLOOKUP(A7,Insumos!A:E,5,FALSE)*B7 -> 2.5
A8: Sal KG | B8: 35 | C8: =VLOOKUP(A8,Insumos!A:E,5,FALSE)*B8 -> 0.14
A9: Amido de milho KG | B9: 35 | C9: =VLOOKUP(A9,Insumos!A:E,5,FALSE)*B9 -> 0.25515
A10: Molho Tarê | B10: 350 | C10: =VLOOKUP(A10,Insumos!A:E,5,FALSE)*B10 -> 10.15
A11: Açucar KG | B11: 170 | C11: =VLOOKUP(A11,Insumos!A:E,5,FALSE)*B11 -> 0.8483
A12: Rendimento | B12: =B5/SUM(B6:B10) -> 0
A14: Cheddar Creme | B14: 1900 | C14: =SUM(C15:C20) -> 54.0481 | D14: =C14/B14 -> 0.028446368
A15: Cheddar Creme Bisnaga 1,5kg | B15: 1500 | C15: =VLOOKUP(A15,Insumos!A:E,5,FALSE)*B15 -> 52.99
A16: Água | B16: 400 | C16: =VLOOKUP(A16,Insumos!A:E,5,FALSE)*B16 -> 0.4
A17: Creme de Cebola KG | B17: 40 | C17: =VLOOKUP(A17,Insumos!A:E,5,FALSE)*B17 -> 0.176
A18: Amido de Milho KG | B18: 6 | C18: =VLOOKUP(A18,Insumos!A:E,5,FALSE)*B18 -> 0.04374
A19: Páprica Defumada KG | B19: 10 | C19: =VLOOKUP(A19,Insumos!A:E,5,FALSE)*B19 -> 0.3
A20: Glutamato Monossódico KG | B20: 2 | C20: =VLOOKUP(A20,Insumos!A:E,5,FALSE)*B20 -> 0.13836
A21: Rendimento | B21: =B13/SUM(B14:B19) -> 0
A23: Creme de Gorgonzola | B23: 2000 | C23: =SUM(C24:C29) -> 72.703245 | D23: =C23/B23 -> 0.036351622
A24: Gorgonzola KG | B24: 1000 | C24: =VLOOKUP(A24,Insumos!A:E,5,FALSE)*B24 -> 53
A25: Creme de Leite UHT | B25: 1000 | C25: =VLOOKUP(A25,Insumos!A:E,5,FALSE)*B25 -> 14.271845
A26: Noz Moscada kg | B26: 6 | C26: =VLOOKUP(A26,Insumos!A:E,5,FALSE)*B26 -> 4.8
A27: Sal KG | B27: 8 | C27: =VLOOKUP(A27,Insumos!A:E,5,FALSE)*B27 -> 0.032
A28: Açucar KG | B28: 60 | C28: =VLOOKUP(A28,Insumos!A:E,5,FALSE)*B28 -> 0.2994
A29: Citrato de Sódio KG | B29: 10 | C29: =VLOOKUP(A29,Insumos!A:E,5,FALSE)*B29 -> 0.3
A30: Rendimento | B30: =B22/SUM(B23:B28) -> 0
A32: Pasta de Cebola Roxa | B32: 600 | C32: =SUM(C33:C34) -> 5.7482759 | D32: =C32/B32 -> 0.0095804598
A33: Cebola Roxa KG | B33: 1000 | C33: =VLOOKUP(A33,Insumos!A:E,5,FALSE)*B33 -> 4.5
A34: Óleo de Algodão | B34: 100 | C34: =VLOOKUP(A34,Insumos!A:E,5,FALSE)*B34 -> 1.2482759
A35: Sal KG | B35: 66 | C35: =VLOOKUP(A35,Insumos!A:E,5,FALSE)*B35 -> 0.264
A36: Rendimento | B36: =B31/SUM(B32:B34) -> 0
A38: Mirocley | B38: 8000 | C38: =SUM(C39:C45) -> 122.22723 | D38: =C38/B38 -> 0.015278403
A39: Pasta de Cebola Roxa | B39: 150 | C39: =VLOOKUP(A39,Insumos!A:E,5,FALSE)*B39 -> 1.437069
A40: Picles KG | B40: 150 | C40: =VLOOKUP(A40,Insumos!A:E,5,FALSE)*B40 -> 6.86625
A41: Mostarda | B41: 150 | C41: =VLOOKUP(A41,Insumos!A:E,5,FALSE)*B41 -> 1.6625
A42: Açucar KG | B42: 400 | C42: =VLOOKUP(A42,Insumos!A:E,5,FALSE)*B42 -> 1.996
A43: Extrato de Tomate KG | B43: 400 | C43: =VLOOKUP(A43,Insumos!A:E,5,FALSE)*B43 -> 5.9076923
A44: Ketchup Galão | B44: 800 | C44: =VLOOKUP(A44,Insumos!A:E,5,FALSE)*B44 -> 15.022
A45: Maionese | B45: 6000 | C45: =VLOOKUP(A45,Insumos!A:E,5,FALSE)*B45 -> 89.335714
A46: Rendimento | B46: =B37/SUM(B38:B44) -> 0
A48: Molho do Frango | B48: 4895 | C48: =SUM(C49:C57) -> 87.558707 | D48: =C48/B48 -> 0.017887376
A49: Maionese | B49: 3000 | C49: =VLOOKUP(A49,Insumos!A:E,5,FALSE)*B49 -> 44.667857
A50: Iogurte Integral Natural | B50: 1000 | C50: =VLOOKUP(A50,Insumos!A:E,5,FALSE)*B50 -> 17.5
A51: Cebola Roxa KG | B51: 200 | C51: =VLOOKUP(A51,Insumos!A:E,5,FALSE)*B51 -> 0.9
A52: Picles KG | B52: 200 | C52: =VLOOKUP(A52,Insumos!A:E,5,FALSE)*B52 -> 9.155
A53: Alcaparras | B53: 200 | C53: =VLOOKUP(A53,Insumos!A:E,5,FALSE)*B53 -> 12
A54: Limão | B54: 90 | C54: =VLOOKUP(A54,Insumos!A:E,5,FALSE)*B54 -> 0.45
A55: Limão Sciciliano | B55: 120 | C55: =VLOOKUP(A55,Insumos!A:E,5,FALSE)*B55 -> 1.44
A56: Salsa KG | B56: 200 | C56: =VLOOKUP(A56,Insumos!A:E,5,FALSE)*B56 -> 0.996
A57: Alho KG | B57: 15 | C57: =VLOOKUP(A57,Insumos!A:E,5,FALSE)*B57 -> 0.44985
A58: Rendimento | B58: 1
A60: Bacon Frito | B60: 296 | C60: =C61 -> 43 | D60: =C60/B60 -> 0.14527027
A61: Bacon Fatiado KG | B61: 1000 | C61: =VLOOKUP(A61,Insumos!A:E,5,FALSE)*B61 -> 43
A62: Rendimento | B62: =B59/B60 -> 0
A64: Bacon Dose | B64: 1 | C64: =C65 -> 2.9054054 | D64: =C64/B64 -> 2.9054054
A65: Bacon Frito | B65: 20 | C65: =VLOOKUP(A65,Insumos!A:E,5,FALSE)*B65 -> 2.9054054
A67: Bacon Batatas | B67: 1 | C67: =C68 -> 4.3581081 | D67: =C67/B67 -> 4.3581081
A68: Bacon Frito | B68: 30 | C68: =VLOOKUP(A68,Insumos!A:E,5,FALSE)*B68 -> 4.3581081
A70: Mussarela Fatia | B70: 1 | C70: =C71 -> 0.6798 | D70: =C70/B70 -> 0.6798
A71: Mussarela KG | B71: 20 | C71: =VLOOKUP(A71,Insumos!A:E,5,FALSE)*B71 -> 0.6798
A73: Cheddar Fatia | B73: 1 | C73: =C74 -> 0.50386 | D73: =C73/B73 -> 0.50386 | M73: Adicional Onion Rings | N73: 4 | O73: =N72*$B$80 -> 0
A74: Cheddar KG | B74: 14 | C74: =VLOOKUP(A74,Insumos!A:E,5,FALSE)*B74 -> 0.50386 | M74: Onion P | N74: 8 | O74: =N73*$B$80 -> 4
M75: Onion M | N75: 12 | O75: =N74*$B$80 -> 8
A76: Batata Frita 100g | B76: 1 | C76: =C77 -> 2.3523077 | D76: =C76/B76 -> 2.3523077 | M76: Onion G | N76: 20 | O76: =N75*$B$80 -> 12
A77: Batata Congelada KG | B77: =100/0.65 -> 153.84615 | C77: =VLOOKUP(A77,Insumos!A:E,5,FALSE)*B77 -> 2.3523077
A78: Rendimento | B78: 0.65 | M78: Nuggets P | N78: 8 | O78: =N77*$B$83 -> 0
M79: Nuggets M | N79: 15 | O79: =N78*$B$83 -> 8
A80: Onion Ring Un. | B80: 1 | C80: =C81 -> 0.297 | D80: =C80/B80 -> 0.297 | M80: Nuggets G | N80: 30 | O80: =N79*$B$83 -> 15
A81: Onion Rings KG | B81: 16.5 | C81: =VLOOKUP(A81,Insumos!A:E,5,FALSE)*B81 -> 0.297
A83: Nuggets Un. | B83: 1 | C83: =C84 -> 0.46396269 | D83: =C83/B83 -> 0.46396269
A84: Nuggets KG | B84: =263.5/13 -> 20.269231 | C84: =VLOOKUP(A84,Insumos!A:E,5,FALSE)*B84 -> 0.46396269
A86: Smash Burger | B86: 1 | C86: =C87 -> 1.9992 | D86: =C86/B86 -> 1.9992
A87: Carne Moída KG | B87: 80 | C87: =VLOOKUP(A87,Insumos!A:E,5,FALSE)*B87 -> 1.9992
A89: Picles Porção | B89: 1 | C89: =C90 -> 1.144375 | D89: =C89/B89 -> 1.144375
A90: Picles kg | B90: 25 | C90: =VLOOKUP(A90,Insumos!A:E,5,FALSE)*B90 -> 1.144375
A92: Cebola roxa Porção | B92: 1 | C92: =C93 -> 0.0675 | D92: =C92/B92 -> 0.0675
A93: Cebola Roxa KG | B93: 15 | C93: =VLOOKUP(A93,Insumos!A:E,5,FALSE)*B93 -> 0.0675
A95: Alface Porção | B95: 1 | C95: =C96 -> 0.723 | D95: =C95/B95 -> 0.723
A96: Alface KG | B96: 30 | C96: =VLOOKUP(A96,Insumos!A:E,5,FALSE)*B96 -> 0.723
A98: Tomate Porção | B98: 1 | C98: =C99 -> 0.24 | D98: =C98/B98 -> 0.24
A99: Tomate KG | B99: 40 | C99: =VLOOKUP(A99,Insumos!A:E,5,FALSE)*B99 -> 0.24
A101: Tomate Ralado Porção | B101: 1 | C101: =C102 -> 0.3 | D101: =C101/B101 -> 0.3
A102: Tomate KG | B102: 50 | C102: =VLOOKUP(A102,Insumos!A:E,5,FALSE)*B102 -> 0.3
A104: Dose Mirocley | B104: 1 | C104: =C105 -> 0.28265046 | D104: =C104/B104 -> 0.28265046
A105: Mirocley | B105: 18.5 | C105: =VLOOKUP(A105,Insumos!A:E,5,FALSE)*B105 -> 0.28265046
A107: Dose Barbecue | B107: 1 | C107: =C108 -> 0.461575 | D107: =C107/B107 -> 0.461575
A108: Barbecue KG | B108: 18.5 | C108: =VLOOKUP(A108,Insumos!A:E,5,FALSE)*B108 -> 0.461575
A111: Cebola Caramelizada Porção | B111: 1 | C111: =C112 -> 0.50084535 | D111: =C111/B111 -> 0.50084535
A112: Cebola Caramelizada | B112: 50 | C112: =VLOOKUP(A112,Insumos!A:E,5,FALSE)*B112 -> 0.50084535
A114: Creme de Gorgonzola Porção | B114: 1 | C114: =C115 -> 1.4540649 | D114: =C114/B114 -> 1.4540649
A115: Creme de Gorgonzola | B115: 40 | C115: =VLOOKUP(A115,Insumos!A:E,5,FALSE)*B115 -> 1.4540649
A117: Priscilo KG | B117: =SUM(B118:B123) -> 4560 | C117: =SUM(C118:C123) -> 52.665 | D117: =C117/B117 -> 0.011549342
A118: Grão de Bico KG | B118: 2000 | C118: =VLOOKUP(A118,Insumos!A:E,5,FALSE)*B118 -> 45.5
A119: Água | B119: 2000 | C119: =VLOOKUP(A119,Insumos!A:E,5,FALSE)*B119 -> 2
A120: Sal KG | B120: 80 | C120: =VLOOKUP(A120,Insumos!A:E,5,FALSE)*B120 -> 0.32
A121: Alho KG | B121: 100 | C121: =VLOOKUP(A121,Insumos!A:E,5,FALSE)*B121 -> 2.999
A122: Salsa KG | B122: 300 | C122: =VLOOKUP(A122,Insumos!A:E,5,FALSE)*B122 -> 1.494
A123: Creme de Cebola KG | B123: 80 | C123: =VLOOKUP(A123,Insumos!A:E,5,FALSE)*B123 -> 0.352
A125: Priscilo UN. | B125: 1 | C125: =C126 -> 1.3859211 | D125: =C125/B125 -> 1.3859211
A126: Priscilo KG | B126: 120 | C126: =VLOOKUP(A126,Insumos!A:E,5,FALSE)*B126 -> 1.3859211
...

Sheet Lanches
B1: Unidades | C1: CMV
A2: Simples | C2: =SUM(C3:C7) -> 4.6137105
A3: Pão Un. | B3: 1 | C3: =IFERROR(VLOOKUP(A3,Insumos!A:E,5,FALSE)*B3,"") -> 1.7
A4: Smash Burger | B4: 1 | C4: =IFERROR(VLOOKUP(A4,Insumos!A:E,5,FALSE)*B4,"") -> 1.9992
A5: Cheddar Fatia | B5: 1 | C5: =IFERROR(VLOOKUP(A5,Insumos!A:E,5,FALSE)*B5,"") -> 0.50386
A6: Dose Mirocley | B6: 1 | C6: =IFERROR(VLOOKUP(A6,Insumos!A:E,5,FALSE)*B6,"") -> 0.28265046
A7: Papel Acoplado | B7: 1 | C7: =IFERROR(VLOOKUP(A7,Insumos!A:E,5,FALSE)*B7,"") -> 0.128
A9: Duplo | C9: =SUM(C10:C14) -> 7.1167705
A10: Pão Un. | B10: 1 | C10: =IFERROR(VLOOKUP(A10,Insumos!A:E,5,FALSE)*B10,"") -> 1.7
A11: Smash Burger | B11: 2 | C11: =IFERROR(VLOOKUP(A11,Insumos!A:E,5,FALSE)*B11,"") -> 3.9984
A12: Cheddar Fatia | B12: 2 | C12: =IFERROR(VLOOKUP(A12,Insumos!A:E,5,FALSE)*B12,"") -> 1.00772
A13: Dose Mirocley | B13: 1 | C13: =IFERROR(VLOOKUP(A13,Insumos!A:E,5,FALSE)*B13,"") -> 0.28265046
A14: Papel Acoplado | B14: 1 | C14: =IFERROR(VLOOKUP(A14,Insumos!A:E,5,FALSE)*B14,"") -> 0.128
A16: Triplo | C16: =SUM(C17:C21) -> 9.6198305
A17: Pão Un. | B17: 1 | C17: =IFERROR(VLOOKUP(A17,Insumos!A:E,5,FALSE)*B17,"") -> 1.7
A18: Smash Burger | B18: 3 | C18: =IFERROR(VLOOKUP(A18,Insumos!A:E,5,FALSE)*B18,"") -> 5.9976
A19: Cheddar Fatia | B19: 3 | C19: =IFERROR(VLOOKUP(A19,Insumos!A:E,5,FALSE)*B19,"") -> 1.51158
A20: Dose Mirocley | B20: 1 | C20: =IFERROR(VLOOKUP(A20,Insumos!A:E,5,FALSE)*B20,"") -> 0.28265046
A21: Papel Acoplado | B21: 1 | C21: =IFERROR(VLOOKUP(A21,Insumos!A:E,5,FALSE)*B21,"") -> 0.128
A23: DBS | C23: =SUM(C24:C32) -> 11.052676
A24: Pão Un. | B24: 1 | C24: =IFERROR(VLOOKUP(A24,Insumos!A:E,5,FALSE)*B24,"") -> 1.7
A25: Smash Burger | B25: 2 | C25: =IFERROR(VLOOKUP(A25,Insumos!A:E,5,FALSE)*B25,"") -> 3.9984
A26: Cheddar Fatia | B26: 2 | C26: =IFERROR(VLOOKUP(A26,Insumos!A:E,5,FALSE)*B26,"") -> 1.00772
A27: Dose Mirocley | B27: 1 | C27: =IFERROR(VLOOKUP(A27,Insumos!A:E,5,FALSE)*B27,"") -> 0.28265046
A28: Cebola Roxa Porção | B28: 1 | C28: =IFERROR(VLOOKUP(A28,Insumos!A:E,5,FALSE)*B28,"") -> 0.0675
A29: Alface Porção | B29: 1 | C29: =IFERROR(VLOOKUP(A29,Insumos!A:E,5,FALSE)*B29,"") -> 0.723
A30: Tomate Porção | B30: 1 | C30: =IFERROR(VLOOKUP(A30,Insumos!A:E,5,FALSE)*B30,"") -> 0.24
A31: Bacon Dose | B31: 1 | C31: =IFERROR(VLOOKUP(A31,Insumos!A:E,5,FALSE)*B31,"") -> 2.9054054
A32: Papel Acoplado | B32: 1 | C32: =IFERROR(VLOOKUP(A32,Insumos!A:E,5,FALSE)*B32,"") -> 0.128
A34: Beicão | C34: =SUM(C35:C40) -> 12.525236
A35: Pão Un. | B35: 1 | C35: =IFERROR(VLOOKUP(A35,Insumos!A:E,5,FALSE)*B35,"") -> 1.7
A36: Smash Burger | B36: 3 | C36: =IFERROR(VLOOKUP(A36,Insumos!A:E,5,FALSE)*B36,"") -> 5.9976
A37: Cheddar Fatia | B37: 3 | C37: =IFERROR(VLOOKUP(A37,Insumos!A:E,5,FALSE)*B37,"") -> 1.51158
A38: Dose Mirocley | B38: 1 | C38: =IFERROR(VLOOKUP(A38,Insumos!A:E,5,FALSE)*B38,"") -> 0.28265046
A39: Bacon Dose | B39: 1 | C39: =IFERROR(VLOOKUP(A39,Insumos!A:E,5,FALSE)*B39,"") -> 2.9054054
A40: Papel Acoplado | B40: 1 | C40: =IFERROR(VLOOKUP(A40,Insumos!A:E,5,FALSE)*B40,"") -> 0.128
A42: Albieri | C42: =SUM(C43:C48) -> 8.94527
A43: Pão Un. | B43: 1 | C43: =IFERROR(VLOOKUP(A43,Insumos!A:E,5,FALSE)*B43,"") -> 1.7
A44: Smash Burger | B44: 2 | C44: =IFERROR(VLOOKUP(A44,Insumos!A:E,5,FALSE)*B44,"") -> 3.9984
A45: Cheddar Fatia | B45: 2 | C45: =IFERROR(VLOOKUP(A45,Insumos!A:E,5,FALSE)*B45,"") -> 1.00772
A46: Dose Barbecue | B46: 2 | C46: =IFERROR(VLOOKUP(A46,Insumos!A:E,5,FALSE)*B46,"") -> 0.92315
A47: Onion Ring Un. | B47: 4 | C47: =IFERROR(VLOOKUP(A47,Insumos!A:E,5,FALSE)*B47,"") -> 1.188
A48: Papel Acoplado | B48: 1 | C48: =IFERROR(VLOOKUP(A48,Insumos!A:E,5,FALSE)*B48,"") -> 0.128
A50: Osvaldão | C50: =SUM(C51:C58) -> 11.397056
A51: Pão Un. | B51: 1 | C51: =IFERROR(VLOOKUP(A51,Insumos!A:E,5,FALSE)*B51,"") -> 1.7
A52: Smash Burger | B52: 2 | C52: =IFERROR(VLOOKUP(A52,Insumos!A:E,5,FALSE)*B52,"") -> 3.9984
A53: Mussarela Fatia | B53: 2 | C53: =IFERROR(VLOOKUP(A53,Insumos!A:E,5,FALSE)*B53,"") -> 1.3596
A54: Bacon Dose | B54: 1 | C54: =IFERROR(VLOOKUP(A54,Insumos!A:E,5,FALSE)*B54,"") -> 2.9054054
A55: Alface Porção | B55: 1 | C55: =IFERROR(VLOOKUP(A55,Insumos!A:E,5,FALSE)*B55,"") -> 0.723
A56: Tomate Ralado Porção | B56: 1 | C56: =IFERROR(VLOOKUP(A56,Insumos!A:E,5,FALSE)*B56,"") -> 0.3
A57: Dose Mirocley | B57: 1 | C57: =IFERROR(VLOOKUP(A57,Insumos!A:E,5,FALSE)*B57,"") -> 0.28265046
A58: Papel Acoplado | B58: 1 | C58: =IFERROR(VLOOKUP(A58,Insumos!A:E,5,FALSE)*B58,"") -> 0.128
A60: Galactocs | C60: =SUM(C61:C68) -> 11.977086
A61: Pão Un. | B61: 1 | C61: =IFERROR(VLOOKUP(A61,Insumos!A:E,5,FALSE)*B61,"") -> 1.7
A62: Smash Burger | B62: 2 | C62: =IFERROR(VLOOKUP(A62,Insumos!A:E,5,FALSE)*B62,"") -> 3.9984
A63: Cheddar Fatia | B63: 2 | C63: =IFERROR(VLOOKUP(A63,Insumos!A:E,5,FALSE)*B63,"") -> 1.00772
A64: Dose Mirocley | B64: 1 | C64: =IFERROR(VLOOKUP(A64,Insumos!A:E,5,FALSE)*B64,"") -> 0.28265046
A65: Creme de Gorgonzola Porção | B65: 1 | C65: =IFERROR(VLOOKUP(A65,Insumos!A:E,5,FALSE)*B65,"") -> 1.4540649
A66: Cebola Caramelizada Porção | B66: 1 | C66: =IFERROR(VLOOKUP(A66,Insumos!A:E,5,FALSE)*B66,"") -> 0.50084535
A67: Bacon Dose | B67: 1 | C67: =IFERROR(VLOOKUP(A67,Insumos!A:E,5,FALSE)*B67,"") -> 2.9054054
A68: Papel Acoplado | B68: 1 | C68: =IFERROR(VLOOKUP(A68,Insumos!A:E,5,FALSE)*B68,"") -> 0.128
A70: Mussarelo | C70: =SUM(C71:C78) -> 11.882621
A71: Pão Un. | B71: 1 | C71: =IFERROR(VLOOKUP(A71,Insumos!A:E,5,FALSE)*B71,"") -> 1.7
A72: Smash Burger | B72: 2 | C72: =IFERROR(VLOOKUP(A72,Insumos!A:E,5,FALSE)*B72,"") -> 3.9984
A73: Cheddar Fatia | B73: 2 | C73: =IFERROR(VLOOKUP(A73,Insumos!A:E,5,FALSE)*B73,"") -> 1.00772
A74: Dose Mirocley | B74: 1 | C74: =IFERROR(VLOOKUP(A74,Insumos!A:E,5,FALSE)*B74,"") -> 0.28265046
A75: Mussarela Fatia | B75: 2 | C75: =IFERROR(VLOOKUP(A75,Insumos!A:E,5,FALSE)*B75,"") -> 1.3596
A76: Cebola Caramelizada Porção | B76: 1 | C76: =IFERROR(VLOOKUP(A76,Insumos!A:E,5,FALSE)*B76,"") -> 0.50084535
A77: Bacon Dose | B77: 1 | C77: =IFERROR(VLOOKUP(A77,Insumos!A:E,5,FALSE)*B77,"") -> 2.9054054
A78: Papel Acoplado | B78: 1 | C78: =IFERROR(VLOOKUP(A78,Insumos!A:E,5,FALSE)*B78,"") -> 0.128
A80: Cidão | C80: =SUM(C81:C91) -> 17.067431
A81: Pão Un. | B81: 1 | C81: =IFERROR(VLOOKUP(A81,Insumos!A:E,5,FALSE)*B81,"") -> 1.7
A82: Smash Burger | B82: 3 | C82: =IFERROR(VLOOKUP(A82,Insumos!A:E,5,FALSE)*B82,"") -> 5.9976
A83: Cheddar Fatia | B83: 5 | C83: =IFERROR(VLOOKUP(A83,Insumos!A:E,5,FALSE)*B83,"") -> 2.5193
A84: Mussarela Fatia | B84: 2 | C84: =IFERROR(VLOOKUP(A84,Insumos!A:E,5,FALSE)*B84,"") -> 1.3596
A85: Bacon Dose | B85: 1 | C85: =IFERROR(VLOOKUP(A85,Insumos!A:E,5,FALSE)*B85,"") -> 2.9054054
A86: Dose Mirocley | B86: 1 | C86: =IFERROR(VLOOKUP(A86,Insumos!A:E,5,FALSE)*B86,"") -> 0.28265046
A87: Cebola Roxa Porção | B87: 1 | C87: =IFERROR(VLOOKUP(A87,Insumos!A:E,5,FALSE)*B87,"") -> 0.0675
A88: Alface Porção | B88: 1 | C88: =IFERROR(VLOOKUP(A88,Insumos!A:E,5,FALSE)*B88,"") -> 0.723
A89: Tomate Porção | B89: 1 | C89: =IFERROR(VLOOKUP(A89,Insumos!A:E,5,FALSE)*B89,"") -> 0.24
A90: Picles Porção | B90: 1 | C90: =IFERROR(VLOOKUP(A90,Insumos!A:E,5,FALSE)*B90,"") -> 1.144375
A91: Papel Acoplado | B91: 1 | C91: =IFERROR(VLOOKUP(A91,Insumos!A:E,5,FALSE)*B91,"") -> 0.128
A93: Priscilo | C93: =SUM(C94:C101) -> 4.9151065
A94: Priscilo UN. | B94: 1 | C94: =IFERROR(VLOOKUP(A94,Insumos!A:E,5,FALSE)*B94,"") -> 1.3859211
A95: Cebola Roxa Porção | B95: 1 | C95: =IFERROR(VLOOKUP(A95,Insumos!A:E,5,FALSE)*B95,"") -> 0.0675
A96: Alface Porção | B96: 1 | C96: =IFERROR(VLOOKUP(A96,Insumos!A:E,5,FALSE)*B96,"") -> 0.723
A97: Picles Porção | B97: 1 | C97: =IFERROR(VLOOKUP(A97,Insumos!A:E,5,FALSE)*B97,"") -> 1.144375
A98: Cheddar Fatia | B98: 1 | C98: =IFERROR(VLOOKUP(A98,Insumos!A:E,5,FALSE)*B98,"") -> 0.50386
A99: Mussarela Fatia | B99: 1 | C99: =IFERROR(VLOOKUP(A99,Insumos!A:E,5,FALSE)*B99,"") -> 0.6798
A100: Dose Mirocley | B100: 1 | C100: =IFERROR(VLOOKUP(A100,Insumos!A:E,5,FALSE)*B100,"") -> 0.28265046
A101: Papel Acoplado | B101: 1 | C101: =IFERROR(VLOOKUP(A101,Insumos!A:E,5,FALSE)*B101,"") -> 0.128
A103: Vintão | C103: =SUM(C104:C111) -> 8.1472705
A104: Pão Un. | B104: 1 | C104: =IFERROR(VLOOKUP(A104,Insumos!A:E,5,FALSE)*B104,"") -> 1.7
A105: Smash Burger | B105: 2 | C105: =IFERROR(VLOOKUP(A105,Insumos!A:E,5,FALSE)*B105,"") -> 3.9984
A106: Cheddar Fatia | B106: 2 | C106: =IFERROR(VLOOKUP(A106,Insumos!A:E,5,FALSE)*B106,"") -> 1.00772
A107: Dose Mirocley | B107: 1 | C107: =IFERROR(VLOOKUP(A107,Insumos!A:E,5,FALSE)*B107,"") -> 0.28265046
A108: Cebola Roxa Porção | B108: 1 | C108: =IFERROR(VLOOKUP(A108,Insumos!A:E,5,FALSE)*B108,"") -> 0.0675
A109: Alface Porção | B109: 1 | C109: =IFERROR(VLOOKUP(A109,Insumos!A:E,5,FALSE)*B109,"") -> 0.723
A110: Tomate Porção | B110: 1 | C110: =IFERROR(VLOOKUP(A110,Insumos!A:E,5,FALSE)*B110,"") -> 0.24
A111: Papel Acoplado | B111: 1 | C111: =IFERROR(VLOOKUP(A111,Insumos!A:E,5,FALSE)*B111,"") -> 0.128
...

Sheet Porções
C1: CMV
A2: Batata P | B2: 1 | C2: =SUM(C3:C5) -> 3.2723077
A3: Batata Frita 100g | B3: 1 | C3: =IFERROR(VLOOKUP(A3,Insumos!A:E,5,FALSE)*B3,"") -> 2.3523077
A4: Caixa de Fritura P | B4: 1 | C4: =IFERROR(VLOOKUP(A4,Insumos!A:E,5,FALSE)*B4,"") -> 0.86
A5: Lacre | B5: 1 | C5: =IFERROR(VLOOKUP(A5,Insumos!A:E,5,FALSE)*B5,"") -> 0.06
A7: Batata M | B7: 1 | C7: =SUM(C8:C10) -> 5.6246154
A8: Batata Frita 100g | B8: 2 | C8: =IFERROR(VLOOKUP(A8,Insumos!A:E,5,FALSE)*B8,"") -> 4.7046154
A9: Caixa de Fritura P | B9: 1 | C9: =IFERROR(VLOOKUP(A9,Insumos!A:E,5,FALSE)*B9,"") -> 0.86
A10: Lacre | B10: 1 | C10: =IFERROR(VLOOKUP(A10,Insumos!A:E,5,FALSE)*B10,"") -> 0.06
A12: Batata G | B12: 1 | C12: =SUM(C13:C15) -> 10.329231
A13: Batata Frita 100g | B13: 4 | C13: =IFERROR(VLOOKUP(A13,Insumos!A:E,5,FALSE)*B13,"") -> 9.4092308
A14: Caixa de Fritura G | B14: 1 | C14: =IFERROR(VLOOKUP(A14,Insumos!A:E,5,FALSE)*B14,"") -> 0.86
A15: Lacre | B15: 1 | C15: =IFERROR(VLOOKUP(A15,Insumos!A:E,5,FALSE)*B15,"") -> 0.06
A17: Onion Rings P | B17: 1 | C17: =SUM(C18:C20) -> 3.296
A18: Onion Ring Un. | B18: 8 | C18: =IFERROR(VLOOKUP(A18,Insumos!A:E,5,FALSE)*B18,"") -> 2.376
A19: Caixa de Fritura P | B19: 1 | C19: =IFERROR(VLOOKUP(A19,Insumos!A:E,5,FALSE)*B19,"") -> 0.86
A20: Lacre | B20: 1 | C20: =IFERROR(VLOOKUP(A20,Insumos!A:E,5,FALSE)*B20,"") -> 0.06
A22: Onion Rings M | B22: 1 | C22: =SUM(C23:C25) -> 4.484
A23: Onion Ring Un. | B23: 12 | C23: =IFERROR(VLOOKUP(A23,Insumos!A:E,5,FALSE)*B23,"") -> 3.564
A24: Caixa de Fritura P | B24: 1 | C24: =IFERROR(VLOOKUP(A24,Insumos!A:E,5,FALSE)*B24,"") -> 0.86
A25: Lacre | B25: 1 | C25: =IFERROR(VLOOKUP(A25,Insumos!A:E,5,FALSE)*B25,"") -> 0.06
A27: Onion Rings G | B27: 1 | C27: =SUM(C28:C30) -> 6.86
A28: Onion Ring Un. | B28: 20 | C28: =IFERROR(VLOOKUP(A28,Insumos!A:E,5,FALSE)*B28,"") -> 5.94
A29: Caixa de Fritura G | B29: 1 | C29: =IFERROR(VLOOKUP(A29,Insumos!A:E,5,FALSE)*B29,"") -> 0.86
A30: Lacre | B30: 1 | C30: =IFERROR(VLOOKUP(A30,Insumos!A:E,5,FALSE)*B30,"") -> 0.06
A32: Nuggets P | B32: 1 | C32: =SUM(C33:C35) -> 4.6317015
A33: Nuggets Un. | B33: 8 | C33: =IFERROR(VLOOKUP(A33,Insumos!A:E,5,FALSE)*B33,"") -> 3.7117015
A34: Caixa de Fritura P | B34: 1 | C34: =IFERROR(VLOOKUP(A34,Insumos!A:E,5,FALSE)*B34,"") -> 0.86
A35: Lacre | B35: 1 | C35: =IFERROR(VLOOKUP(A35,Insumos!A:E,5,FALSE)*B35,"") -> 0.06
A37: Nuggets M | B37: 1 | C37: =SUM(C38:C40) -> 7.8794404
A38: Nuggets Un. | B38: 15 | C38: =IFERROR(VLOOKUP(A38,Insumos!A:E,5,FALSE)*B38,"") -> 6.9594404
A39: Caixa de Fritura P | B39: 1 | C39: =IFERROR(VLOOKUP(A39,Insumos!A:E,5,FALSE)*B39,"") -> 0.86
A40: Lacre | B40: 1 | C40: =IFERROR(VLOOKUP(A40,Insumos!A:E,5,FALSE)*B40,"") -> 0.06
A42: Nuggets G | B42: 1 | C42: =SUM(C43:C45) -> 14.838881
A43: Nuggets Un. | B43: 30 | C43: =IFERROR(VLOOKUP(A43,Insumos!A:E,5,FALSE)*B43,"") -> 13.918881
A44: Caixa de Fritura P | B44: 1 | C44: =IFERROR(VLOOKUP(A44,Insumos!A:E,5,FALSE)*B44,"") -> 0.86
A45: Lacre | B45: 1 | C45: =IFERROR(VLOOKUP(A45,Insumos!A:E,5,FALSE)*B45,"") -> 0.06
A47: Batatocs Cheddar + Bacon | C47: =SUM(C48:C52) -> 12.542897
A48: Batata Frita 100g | B48: 2 | C48: =IFERROR(VLOOKUP(A48,Insumos!A:E,5,FALSE)*B48,"") -> 4.7046154
A49: Cheddar Creme | B49: 90 | C49: =IFERROR(VLOOKUP(A49,Insumos!A:E,5,FALSE)*B49,"") -> 2.5601732
A50: Bacon Batatas | B50: 1 | C50: =IFERROR(VLOOKUP(A50,Insumos!A:E,5,FALSE)*B50,"") -> 4.3581081
A51: Caixa de Fritura G | B51: 1 | C51: =IFERROR(VLOOKUP(A51,Insumos!A:E,5,FALSE)*B51,"") -> 0.86
A52: Lacre | B52: 1 | C52: =IFERROR(VLOOKUP(A52,Insumos!A:E,5,FALSE)*B52,"") -> 0.06
A54: Batatocs Gorgonzola + Bacon | C54: =SUM(C55:C59) -> 13.254369
A55: Batata Frita 100g | B55: 2 | C55: =IFERROR(VLOOKUP(A55,Insumos!A:E,5,FALSE)*B55,"") -> 4.7046154
A56: Creme de Gorgonzola | B56: 90 | C56: =IFERROR(VLOOKUP(A56,Insumos!A:E,5,FALSE)*B56,"") -> 3.271646
A57: Bacon Batatas | B57: 1 | C57: =IFERROR(VLOOKUP(A57,Insumos!A:E,5,FALSE)*B57,"") -> 4.3581081
A58: Caixa de Fritura G | B58: 1 | C58: =IFERROR(VLOOKUP(A58,Insumos!A:E,5,FALSE)*B58,"") -> 0.86
A59: Lacre | B59: 1 | C59: =IFERROR(VLOOKUP(A59,Insumos!A:E,5,FALSE)*B59,"") -> 0.06
A61: Porção Mista | C61: =SUM(C62:C66) -> 9.3600092
A62: Batata Frita 100g | B62: 1 | C62: =IFERROR(VLOOKUP(A62,Insumos!A:E,5,FALSE)*B62,"") -> 2.3523077
A63: Onion Ring Un. | B63: 8 | C63: =IFERROR(VLOOKUP(A63,Insumos!A:E,5,FALSE)*B63,"") -> 2.376
A64: Nuggets Un. | B64: 8 | C64: =IFERROR(VLOOKUP(A64,Insumos!A:E,5,FALSE)*B64,"") -> 3.7117015
A65: Caixa de Fritura G | B65: 1 | C65: =IFERROR(VLOOKUP(A65,Insumos!A:E,5,FALSE)*B65,"") -> 0.86
A66: Lacre | B66: 1 | C66: =IFERROR(VLOOKUP(A66,Insumos!A:E,5,FALSE)*B66,"") -> 0.06

Sheet Bebidas
A1: Produto | B1: Qtd_Grande | C1: Qtd_Unid | D1: Vlr_Total | E1: Vlr_Médio_Grande | F1: Vlr_Médio_Unid | G1: Preço de Venda Site | H1: Preço de Venda Loja | I1: Preço de Venda Ifood
A2: Trident Menta Envelope 8g CX21 | B2: 1 | C2: 21 | D2: 38.59 | E2: 38.59 | F2: 1.837619 | G2: x | H2: 4 | I2: x
A3: Coquinha 200ml normal | B3: 2 | C3: 24 | D3: 30.06 | E3: 15.03 | F3: 1.2525 | G3: x | H3: 4.5 | I3: x
A4: Coquinha 200ml zero | B4: 2 | C4: 24 | D4: 30.1 | E4: 15.05 | F4: 1.2541667 | G4: x | H4: 4.5 | I4: x
A5: Água Sem Gás | B5: 7 | C5: 84 | D5: 89.67 | E5: 12.81 | F5: 1.0675 | G5: 5 | H5: 5 | I5: 6
A6: Água Com Gás | B6: 7 | C6: 84 | D6: 101.81 | E6: 14.544286 | F6: 1.2120238 | G6: 5 | H6: 5 | I6: 6
A7: Tônica | B7: 1 | C7: 12 | D7: 31 | E7: 31 | F7: 2.5833333 | G7: 5 | H7: 5 | I7: x
A8: Tônica Zero | F8: 2.6075 | G8: 5 | H8: 5 | I8: x
A9: Coca KS Zero | F9: 2.35 | G9: x | H9: 6 | I9: x
A10: Coca KS Original | F10: 2.35 | G10: x | H10: 6 | I10: x
A11: Coca Zero Lata | B11: 33 | C11: 396 | D11: 1000.83 | E11: 30.328182 | F11: 2.5273485 | G11: 7 | H11: 8 | I11: 9
A12: Coca Cola Lata | B12: 16 | C12: 192 | D12: 490.32 | E12: 30.645 | F12: 2.55375 | G12: 7 | H12: 8 | I12: 9
A13: Citrus Lata | B13: 2 | C13: 24 | D13: 61.7 | E13: 30.85 | F13: 2.5708333 | G13: x | H13: 8 | I13: x
A14: Pepsi Black Lata | B14: 1 | C14: 12 | D14: 31.2 | E14: 31.2 | F14: 2.6 | G14: 7 | H14: 8 | I14: x
A15: Guaraná Lata | B15: 7 | C15: 84 | D15: 219.03 | E15: 31.29 | F15: 2.6075 | G15: 7 | H15: 8 | I15: 9
A16: Guaraná Zero Lata | F16: 2.6075 | G16: 7 | H16: 8 | I16: x
A17: Sukita Laranja Lata | F17: 2.6075 | G17: 7 | H17: 8 | I17: x
A18: Coca Zero 600ml | B18: 16 | C18: 192 | D18: 636.92 | E18: 39.8075 | F18: 3.3172917 | G18: 12 | H18: 12 | I18: 12.9
A19: Coca Cola 600ml | B19: 6 | C19: 72 | D19: 239.26 | E19: 39.876667 | F19: 3.3230556 | G19: 12 | H19: 12 | I19: 12.9
A20: Guaraná 600ml | B20: 2 | C20: 24 | D20: 88 | E20: 44 | F20: 3.6666667 | G20: 12 | H20: 12 | I20: 12.9
A21: Guaraná Zero 600ml | F21: 2.6075 | G21: x | H21: 12 | I21: 12.9
A22: Suco Prats Laranja | B22: 36 | C22: 36 | D22: 162 | E22: 4.5 | F22: 4.5 | G22: 14 | H22: 14 | I22: 15
A23: Suco Prats Uva | B23: 24 | C23: 24 | D23: 120 | E23: 5 | F23: 5 | G23: 14 | H23: 14 | I23: 15
A24: Chopp Brahma | B24: 1 | C24: 1 | D24: 748.1 | E24: 748.1 | F24: =(E23/50)/2 -> 0.05 | G24: x | H24: 14 | I24: x
A25: Coca Cola 1L | B25: 8 | C25: 48 | D25: 278.44 | E25: 34.805 | F25: 5.8008333 | G25: x | H25: 15 | I25: x
A26: Cerveja Original 600ml | B26: 4 | C26: 48 | D26: 351.52 | E26: 87.88 | F26: 7.3233333 | G26: x | H26: 16 | I26: x
A27: Coca Zero 2L | B27: 3 | C27: 24 | D27: 195.84 | E27: 65.28 | F27: 8.16 | G27: 20 | H27: 20 | I27: 22
A28: Coca Cola 2L | B28: 4 | C28: 25 | D28: 204.18 | E28: 51.045 | F28: 8.1672 | G28: 20 | H28: 20 | I28: 22

Sheet Sobremesas
B1: Quantidade | C1: CMV
A2: Churros com Sorvete | B2: CMV | C2: =SUM(C3:C4) -> 10.62
A3: Churros Recheados KG | B3: 130 | C3: =VLOOKUP(A3,Insumos!A:E,5,FALSE)*B3 -> 3.9
A4: Sorvete KG | B4: 80 | C4: =VLOOKUP(A4,Insumos!A:E,5,FALSE)*B4 -> 6.72
A5: Calda de Chocolate KG | B5: 30 | C5: =VLOOKUP(A5,Insumos!A:E,5,FALSE)*B5 -> 1.2978
A7: Churros Especial | B7: CMV | C7: =SUM(C8:C9) -> 7.0956
A8: Churros Palito KG | B8: 150 | C8: =VLOOKUP(A8,Insumos!A:E,5,FALSE)*B8 -> 4.5
A9: Calda de Chocolate KG | B9: 60 | C9: =VLOOKUP(A9,Insumos!A:E,5,FALSE)*B9 -> 2.5956
A11: Brownie com Sorvete | B11: CMV | C11: =SUM(C12:C13) -> 13.22
A12: Brownie Lhamaria | B12: 1 | C12: =VLOOKUP(A12,Insumos!A:E,5,FALSE)*B12 -> 6.5
A13: Sorvete KG | B13: 80 | C13: =VLOOKUP(A13,Insumos!A:E,5,FALSE)*B13 -> 6.72
A14: Calda de Chocolate KG | B14: 30 | C14: =VLOOKUP(A14,Insumos!A:E,5,FALSE)*B14 -> 1.2978
A16: Copo de Sorvete | B16: CMV | C16: =SUM(C17:C18) -> 14.7378
A17: Sorvete KG | B17: 160 | C17: =VLOOKUP(A17,Insumos!A:E,5,FALSE)*B17 -> 13.44
A18: Calda de Chocolate KG | B18: 30 | C18: =VLOOKUP(A18,Insumos!A:E,5,FALSE)*B18 -> 1.2978
A20: Churros do And | B20: CMV | C20: =SUM(C21:C22) -> 4.76
A21: Churros Recheados KG | B21: 130 | C21: =VLOOKUP(A21,Insumos!A:E,5,FALSE)*B21 -> 3.9
A22: Caixa de Fritura P | B22: 1 | C22: =VLOOKUP(A22,Insumos!A:E,5,FALSE)*B22 -> 0.86
A26: Cookie Red Velvet Lhamaria | B26: CMV | C26: 6.5
A27: Brownie de Chocolate Lhamaria | B27: CMV | C27: 6.5

Sheet Combos
A1: Insumos | B1: Preparos | C1: Lanches | D1: Porções | E1: Bebidas | F1: Sobremesas | G1: Combos | H1: COMPARAÇÃO DE PREÇOS
A2: ITEM | B2: CMV | C2: PREÇO DE VENDA NO SITE | D2: PREÇO DE VENDA IFOOD | E2: PREÇO DE VENDA NA LOJA
A3: Combo Kids | B3: =SUM(B4:B5) -> 7.8860182 | C3: 35.5 | F3: 35.5
A4: Batata P | B4: =IFERROR(VLOOKUP(A4, Lanches!$A:$C, 3, FALSE), IFERROR(VLOOKUP(A4, 'Porções'!$A:$C, 3, FALSE), IFERROR(VLOOKUP(A4, Bebidas!$A:$F, 6, FALSE), ""))) -> 3.2723077
A5: Simples | B5: =IFERROR(VLOOKUP(A5, Lanches!$A:$C, 3, FALSE), IFERROR(VLOOKUP(A5, 'Porções'!$A:$C, 3, FALSE), IFERROR(VLOOKUP(A5, Bebidas!$A:$F, 6, FALSE), ""))) -> 4.6137105
A6: Coquinha 200ml normal | B6: =IFERROR(VLOOKUP(A6, Lanches!$A:$C, 3, FALSE), IFERROR(VLOOKUP(A6, 'Porções'!$A:$C, 3, FALSE), IFERROR(VLOOKUP(A6, Bebidas!$A:$F, 6, FALSE), ""))) -> 1.2525
A8: Combão Priscilo | B8: =SUM(B9:B10) -> 8.1874142 | C8: 57 | F8: 57
A9: Priscilo | B9: =IFERROR(VLOOKUP(A9, Lanches!$A:$C, 3, FALSE), IFERROR(VLOOKUP(A9, 'Porções'!$A:$C, 3, FALSE), IFERROR(VLOOKUP(A9, Bebidas!$A:$F, 6, FALSE), ""))) -> 4.9151065
A10: Batata P | B10: =IFERROR(VLOOKUP(A10, Lanches!$A:$C, 3, FALSE), IFERROR(VLOOKUP(A10, 'Porções'!$A:$C, 3, FALSE), IFERROR(VLOOKUP(A10, Bebidas!$A:$F, 6, FALSE), ""))) -> 3.2723077
A11: Coca Cola Lata | B11: =IFERROR(VLOOKUP(A11, Lanches!$A:$C, 3, FALSE), IFERROR(VLOOKUP(A11, 'Porções'!$A:$C, 3, FALSE), IFERROR(VLOOKUP(A11, Bebidas!$A:$F, 6, FALSE), ""))) -> 2.55375
A13: Combão Cidão | B13: =SUM(B14:B15) -> 20.339739
A14: Cidão | B14: =IFERROR(VLOOKUP(A14, Lanches!$A:$C, 3, FALSE), IFERROR(VLOOKUP(A14, 'Porções'!$A:$C, 3, FALSE), IFERROR(VLOOKUP(A14, Bebidas!$A:$F, 6, FALSE), ""))) -> 17.067431
A15: Batata P | B15: =IFERROR(VLOOKUP(A15, Lanches!$A:$C, 3, FALSE), IFERROR(VLOOKUP(A15, 'Porções'!$A:$C, 3, FALSE), IFERROR(VLOOKUP(A15, Bebidas!$A:$F, 6, FALSE), ""))) -> 3.2723077
A16: Coca Cola Lata | B16: =IFERROR(VLOOKUP(A16, Lanches!$A:$C, 3, FALSE), IFERROR(VLOOKUP(A16, 'Porções'!$A:$C, 3, FALSE), IFERROR(VLOOKUP(A16, Bebidas!$A:$F, 6, FALSE), ""))) -> 2.55375
A18: Combão Mussarelo | B18: =SUM(B19:B20) -> 15.154929 | C18: 65 | F18: 65
A19: Mussarelo | B19: =IFERROR(VLOOKUP(A19, Lanches!$A:$C, 3, FALSE), IFERROR(VLOOKUP(A19, 'Porções'!$A:$C, 3, FALSE), IFERROR(VLOOKUP(A19, Bebidas!$A:$F, 6, FALSE), ""))) -> 11.882621 | I19: =29.9-13+65 -> 81.9
A20: Batata P | B20: =IFERROR(VLOOKUP(A20, Lanches!$A:$C, 3, FALSE), IFERROR(VLOOKUP(A20, 'Porções'!$A:$C, 3, FALSE), IFERROR(VLOOKUP(A20, Bebidas!$A:$F, 6, FALSE), ""))) -> 3.2723077
A21: Coca Cola Lata | B21: =IFERROR(VLOOKUP(A21, Lanches!$A:$C, 3, FALSE), IFERROR(VLOOKUP(A21, 'Porções'!$A:$C, 3, FALSE), IFERROR(VLOOKUP(A21, Bebidas!$A:$F, 6, FALSE), ""))) -> 2.55375
A23: Combão Osvaldão | B23: =SUM(B24:B25) -> 14.669364 | C23: 61 | F23: 61
A24: Osvaldão | B24: =IFERROR(VLOOKUP(A24, Lanches!$A:$C, 3, FALSE), IFERROR(VLOOKUP(A24, 'Porções'!$A:$C, 3, FALSE), IFERROR(VLOOKUP(A24, Bebidas!$A:$F, 6, FALSE), ""))) -> 11.397056
A25: Batata P | B25: =IFERROR(VLOOKUP(A25, Lanches!$A:$C, 3, FALSE), IFERROR(VLOOKUP(A25, 'Porções'!$A:$C, 3, FALSE), IFERROR(VLOOKUP(A25, Bebidas!$A:$F, 6, FALSE), ""))) -> 3.2723077
A26: Coca Cola Lata | B26: =IFERROR(VLOOKUP(A26, Lanches!$A:$C, 3, FALSE), IFERROR(VLOOKUP(A26, 'Porções'!$A:$C, 3, FALSE), IFERROR(VLOOKUP(A26, Bebidas!$A:$F, 6, FALSE), ""))) -> 2.55375
A28: Combão DBS | B28: =SUM(B29:B30) -> 14.324984 | C28: 60 | F28: 60
A29: DBS | B29: =IFERROR(VLOOKUP(A29, Lanches!$A:$C, 3, FALSE), IFERROR(VLOOKUP(A29, 'Porções'!$A:$C, 3, FALSE), IFERROR(VLOOKUP(A29, Bebidas!$A:$F, 6, FALSE), ""))) -> 11.052676
A30: Batata P | B30: =IFERROR(VLOOKUP(A30, Lanches!$A:$C, 3, FALSE), IFERROR(VLOOKUP(A30, 'Porções'!$A:$C, 3, FALSE), IFERROR(VLOOKUP(A30, Bebidas!$A:$F, 6, FALSE), ""))) -> 3.2723077
A31: Coca Cola Lata | B31: =IFERROR(VLOOKUP(A31, Lanches!$A:$C, 3, FALSE), IFERROR(VLOOKUP(A31, 'Porções'!$A:$C, 3, FALSE), IFERROR(VLOOKUP(A31, Bebidas!$A:$F, 6, FALSE), ""))) -> 2.55375
A33: Combo Vintão | B33: =SUM(B34:B35) -> 11.419578
A34: Vintão | B34: =IFERROR(VLOOKUP(A34, Lanches!$A:$C, 3, FALSE), IFERROR(VLOOKUP(A34, 'Porções'!$A:$C, 3, FALSE), IFERROR(VLOOKUP(A34, Bebidas!$A:$F, 6, FALSE), ""))) -> 8.1472705
A35: Batata P | B35: =IFERROR(VLOOKUP(A35, Lanches!$A:$C, 3, FALSE), IFERROR(VLOOKUP(A35, 'Porções'!$A:$C, 3, FALSE), IFERROR(VLOOKUP(A35, Bebidas!$A:$F, 6, FALSE), ""))) -> 3.2723077
A36: Coca Cola Lata | B36: =IFERROR(VLOOKUP(A36, Lanches!$A:$C, 3, FALSE), IFERROR(VLOOKUP(A36, 'Porções'!$A:$C, 3, FALSE), IFERROR(VLOOKUP(A36, Bebidas!$A:$F, 6, FALSE), ""))) -> 2.55375
A38: Combão Beicão | B38: =SUM(B39:B40) -> 15.797544 | C38: 61 | F38: 61
A39: Beicão | B39: =IFERROR(VLOOKUP(A39, Lanches!$A:$C, 3, FALSE), IFERROR(VLOOKUP(A39, 'Porções'!$A:$C, 3, FALSE), IFERROR(VLOOKUP(A39, Bebidas!$A:$F, 6, FALSE), ""))) -> 12.525236
A40: Batata P | B40: =IFERROR(VLOOKUP(A40, Lanches!$A:$C, 3, FALSE), IFERROR(VLOOKUP(A40, 'Porções'!$A:$C, 3, FALSE), IFERROR(VLOOKUP(A40, Bebidas!$A:$F, 6, FALSE), ""))) -> 3.2723077
A41: Coca Cola Lata | B41: =IFERROR(VLOOKUP(A41, Lanches!$A:$C, 3, FALSE), IFERROR(VLOOKUP(A41, 'Porções'!$A:$C, 3, FALSE), IFERROR(VLOOKUP(A41, Bebidas!$A:$F, 6, FALSE), ""))) -> 2.55375
A43: Combão Galactos | B43: =SUM(B44:B45) -> 15.249394 | C43: 65 | F43: 65
A44: Galactocs | B44: =IFERROR(VLOOKUP(A44, Lanches!$A:$C, 3, FALSE), IFERROR(VLOOKUP(A44, 'Porções'!$A:$C, 3, FALSE), IFERROR(VLOOKUP(A44, Bebidas!$A:$F, 6, FALSE), ""))) -> 11.977086
A45: Batata P | B45: =IFERROR(VLOOKUP(A45, Lanches!$A:$C, 3, FALSE), IFERROR(VLOOKUP(A45, 'Porções'!$A:$C, 3, FALSE), IFERROR(VLOOKUP(A45, Bebidas!$A:$F, 6, FALSE), ""))) -> 3.2723077
A46: Coca Cola Lata | B46: =IFERROR(VLOOKUP(A46, Lanches!$A:$C, 3, FALSE), IFERROR(VLOOKUP(A46, 'Porções'!$A:$C, 3, FALSE), IFERROR(VLOOKUP(A46, Bebidas!$A:$F, 6, FALSE), ""))) -> 2.55375
A48: Combão Albieri | B48: =SUM(B49:B50) -> 12.217578 | C48: 65 | F48: 65
A49: Albieri | B49: =IFERROR(VLOOKUP(A49, Lanches!$A:$C, 3, FALSE), IFERROR(VLOOKUP(A49, 'Porções'!$A:$C, 3, FALSE), IFERROR(VLOOKUP(A49, Bebidas!$A:$F, 6, FALSE), ""))) -> 8.94527
A50: Batata P | B50: =IFERROR(VLOOKUP(A50, Lanches!$A:$C, 3, FALSE), IFERROR(VLOOKUP(A50, 'Porções'!$A:$C, 3, FALSE), IFERROR(VLOOKUP(A50, Bebidas!$A:$F, 6, FALSE), ""))) -> 3.2723077
A51: Coca Cola Lata | B51: =IFERROR(VLOOKUP(A51, Lanches!$A:$C, 3, FALSE), IFERROR(VLOOKUP(A51, 'Porções'!$A:$C, 3, FALSE), IFERROR(VLOOKUP(A51, Bebidas!$A:$F, 6, FALSE), ""))) -> 2.55375
A53: COMBO ALBIERI + DBS | B53: =SUM(B54:B55) -> 19.997946 | C53: 52.99
A54: Albieri | B54: =IFERROR(VLOOKUP(A54, Lanches!$A:$C, 3, FALSE), IFERROR(VLOOKUP(A54, 'Porções'!$A:$C, 3, FALSE), IFERROR(VLOOKUP(A54, Bebidas!$A:$F, 6, FALSE), ""))) -> 8.94527
A55: DBS | B55: =IFERROR(VLOOKUP(A55, Lanches!$A:$C, 3, FALSE), IFERROR(VLOOKUP(A55, 'Porções'!$A:$C, 3, FALSE), IFERROR(VLOOKUP(A55, Bebidas!$A:$F, 6, FALSE), ""))) -> 11.052676
A57: OSVALDÃO + SIMPLES | B57: =SUM(B58:B59) -> 16.010766 | C57: 48.99
A58: Simples | B58: =IFERROR(VLOOKUP(A58, Lanches!$A:$C, 3, FALSE), IFERROR(VLOOKUP(A58, 'Porções'!$A:$C, 3, FALSE), IFERROR(VLOOKUP(A58, Bebidas!$A:$F, 6, FALSE), ""))) -> 4.6137105
A59: Osvaldão | B59: =IFERROR(VLOOKUP(A59, Lanches!$A:$C, 3, FALSE), IFERROR(VLOOKUP(A59, 'Porções'!$A:$C, 3, FALSE), IFERROR(VLOOKUP(A59, Bebidas!$A:$F, 6, FALSE), ""))) -> 11.397056
A61: GALACTOCS + DUPLO | B61: =SUM(B62:B63) -> 19.093857 | C61: 55.99
A62: Duplo | B62: =IFERROR(VLOOKUP(A62, Lanches!$A:$C, 3, FALSE), IFERROR(VLOOKUP(A62, 'Porções'!$A:$C, 3, FALSE), IFERROR(VLOOKUP(A62, Bebidas!$A:$F, 6, FALSE), ""))) -> 7.1167705
A63: Galactocs | B63: =IFERROR(VLOOKUP(A63, Lanches!$A:$C, 3, FALSE), IFERROR(VLOOKUP(A63, 'Porções'!$A:$C, 3, FALSE), IFERROR(VLOOKUP(A63, Bebidas!$A:$F, 6, FALSE), ""))) -> 11.977086
A65: MUSSARELO + GALACTOCS + OSVALDAO | B65: =SUM(B66:B68) -> 35.256763 | C65: 91.99
A66: Mussarelo | B66: =IFERROR(VLOOKUP(A66, Lanches!$A:$C, 3, FALSE), IFERROR(VLOOKUP(A66, 'Porções'!$A:$C, 3, FALSE), IFERROR(VLOOKUP(A66, Bebidas!$A:$F, 6, FALSE), ""))) -> 11.882621
A67: Galactocs | B67: =IFERROR(VLOOKUP(A67, Lanches!$A:$C, 3, FALSE), IFERROR(VLOOKUP(A67, 'Porções'!$A:$C, 3, FALSE), IFERROR(VLOOKUP(A67, Bebidas!$A:$F, 6, FALSE), ""))) -> 11.977086
A68: Osvaldão | B68: =IFERROR(VLOOKUP(A68, Lanches!$A:$C, 3, FALSE), IFERROR(VLOOKUP(A68, 'Porções'!$A:$C, 3, FALSE), IFERROR(VLOOKUP(A68, Bebidas!$A:$F, 6, FALSE), ""))) -> 11.397056

Sheet COMPARAÇÃO DE PREÇOS
A1: Insumos | B1: Preparos | C1: Lanches | D1: Porções | E1: Bebidas | F1: Sobremesas | G1: Combos | H1: COMPARAÇÃO DE PREÇOS
A3: NOME DO PRODUTO DO CARDÁPIO | B3: CMV + EMBALAGEM | C3: PREÇO DE VENDA NO SITE | D3: PREÇO DE VENDA IFOOD | E3: PREÇO DE VENDA NA LOJA | F3: CMV SITE | G3: CMV IFOOD | H3: CMV LOJA
A4: Simples | B4: =IFERROR(VLOOKUP(A4, Lanches!$A:$C, 3, FALSE), IFERROR(VLOOKUP(A4, 'Porções'!$A:$C, 3, FALSE), IFERROR(VLOOKUP(A4, Bebidas!$A:$F, 6, FALSE), IFERROR(VLOOKUP(A4, Sobremesas!$A:$F, 3, FALSE), IFERROR(VLOOKUP(A4, Combos!$A:$F, 2, FALSE), ""))))) -> 4.6137105 | C4: 23 | D4: 34 | E4: 23 | F4: =IF(OR(B4="",C4=""),"",B4/C4) -> 0.20059611 | G4: =IF(OR(B4="",D4=""),"",B4/D4) -> 0.13569737 | H4: =IF(OR(B4="",E4=""),"",B4/E4) -> 0.20059611
A5: Duplo | B5: =IFERROR(VLOOKUP(A5, Lanches!$A:$C, 3, FALSE), IFERROR(VLOOKUP(A5, 'Porções'!$A:$C, 3, FALSE), IFERROR(VLOOKUP(A5, Bebidas!$A:$F, 6, FALSE), IFERROR(VLOOKUP(A5, Sobremesas!$A:$F, 3, FALSE), IFERROR(VLOOKUP(A5, Combos!$A:$F, 2, FALSE), ""))))) -> 7.1167705 | C5: 28 | D5: 39 | E5: 28 | F5: =IF(OR(B5="",C5=""),"",B5/C5) -> 0.25417037 | G5: =IF(OR(B5="",D5=""),"",B5/D5) -> 0.18248129 | H5: =IF(OR(B5="",E5=""),"",B5/E5) -> 0.25417037
A6: Triplo | B6: =IFERROR(VLOOKUP(A6, Lanches!$A:$C, 3, FALSE), IFERROR(VLOOKUP(A6, 'Porções'!$A:$C, 3, FALSE), IFERROR(VLOOKUP(A6, Bebidas!$A:$F, 6, FALSE), IFERROR(VLOOKUP(A6, Sobremesas!$A:$F, 3, FALSE), IFERROR(VLOOKUP(A6, Combos!$A:$F, 2, FALSE), ""))))) -> 9.6198305 | C6: 33 | D6: 45 | E6: 33 | F6: =IF(OR(B6="",C6=""),"",B6/C6) -> 0.29151001 | G6: =IF(OR(B6="",D6=""),"",B6/D6) -> 0.21377401 | H6: =IF(OR(B6="",E6=""),"",B6/E6) -> 0.29151001
A7: DBS | B7: =IFERROR(VLOOKUP(A7, Lanches!$A:$C, 3, FALSE), IFERROR(VLOOKUP(A7, 'Porções'!$A:$C, 3, FALSE), IFERROR(VLOOKUP(A7, Bebidas!$A:$F, 6, FALSE), IFERROR(VLOOKUP(A7, Sobremesas!$A:$F, 3, FALSE), IFERROR(VLOOKUP(A7, Combos!$A:$F, 2, FALSE), ""))))) -> 11.052676 | C7: 38 | D7: 57.9 | E7: 38 | F7: =IF(OR(B7="",C7=""),"",B7/C7) -> 0.29085989 | G7: =IF(OR(B7="",D7=""),"",B7/D7) -> 0.1908925 | H7: =IF(OR(B7="",E7=""),"",B7/E7) -> 0.29085989
A8: Beicão | B8: =IFERROR(VLOOKUP(A8, Lanches!$A:$C, 3, FALSE), IFERROR(VLOOKUP(A8, 'Porções'!$A:$C, 3, FALSE), IFERROR(VLOOKUP(A8, Bebidas!$A:$F, 6, FALSE), IFERROR(VLOOKUP(A8, Sobremesas!$A:$F, 3, FALSE), IFERROR(VLOOKUP(A8, Combos!$A:$F, 2, FALSE), ""))))) -> 12.525236 | C8: 39 | D8: 59.9 | E8: 39 | F8: =IF(OR(B8="",C8=""),"",B8/C8) -> 0.32115989 | G8: =IF(OR(B8="",D8=""),"",B8/D8) -> 0.20910244 | H8: =IF(OR(B8="",E8=""),"",B8/E8) -> 0.32115989
A9: Albieri | B9: =IFERROR(VLOOKUP(A9, Lanches!$A:$C, 3, FALSE), IFERROR(VLOOKUP(A9, 'Porções'!$A:$C, 3, FALSE), IFERROR(VLOOKUP(A9, Bebidas!$A:$F, 6, FALSE), IFERROR(VLOOKUP(A9, Sobremesas!$A:$F, 3, FALSE), IFERROR(VLOOKUP(A9, Combos!$A:$F, 2, FALSE), ""))))) -> 8.94527 | C9: 43 | D9: 51.9 | E9: 43 | F9: =IF(OR(B9="",D9=""),"",B9/D9) -> 0.17235588 | G9: =IF(OR(B9="",D9=""),"",B9/D9) -> 0.17235588 | H9: =IF(OR(B9="",E9=""),"",B9/E9) -> 0.20802953
A10: Osvaldão | B10: =IFERROR(VLOOKUP(A10, Lanches!$A:$C, 3, FALSE), IFERROR(VLOOKUP(A10, 'Porções'!$A:$C, 3, FALSE), IFERROR(VLOOKUP(A10, Bebidas!$A:$F, 6, FALSE), IFERROR(VLOOKUP(A10, Sobremesas!$A:$F, 3, FALSE), IFERROR(VLOOKUP(A10, Combos!$A:$F, 2, FALSE), ""))))) -> 11.397056 | C10: 39 | D10: 51.9 | E10: 39 | F10: =IF(OR(B10="",C10=""),"",B10/C10) -> 0.2922322 | G10: =IF(OR(B10="",D10=""),"",B10/D10) -> 0.21959645 | H10: =IF(OR(B10="",E10=""),"",B10/E10) -> 0.2922322
A11: Galactocs | B11: =IFERROR(VLOOKUP(A11, Lanches!$A:$C, 3, FALSE), IFERROR(VLOOKUP(A11, 'Porções'!$A:$C, 3, FALSE), IFERROR(VLOOKUP(A11, Bebidas!$A:$F, 6, FALSE), IFERROR(VLOOKUP(A11, Sobremesas!$A:$F, 3, FALSE), IFERROR(VLOOKUP(A11, Combos!$A:$F, 2, FALSE), ""))))) -> 11.977086 | C11: 43 | D11: 51.9 | E11: 43 | F11: =IF(OR(B11="",C11=""),"",B11/C11) -> 0.27853689 | G11: =IF(OR(B11="",D11=""),"",B11/D11) -> 0.23077237 | H11: =IF(OR(B11="",E11=""),"",B11/E11) -> 0.27853689
A12: Mussarelo | B12: =IFERROR(VLOOKUP(A12, Lanches!$A:$C, 3, FALSE), IFERROR(VLOOKUP(A12, 'Porções'!$A:$C, 3, FALSE), IFERROR(VLOOKUP(A12, Bebidas!$A:$F, 6, FALSE), IFERROR(VLOOKUP(A12, Sobremesas!$A:$F, 3, FALSE), IFERROR(VLOOKUP(A12, Combos!$A:$F, 2, FALSE), ""))))) -> 11.882621 | C12: 43 | D12: 53.7 | E12: 43 | F12: =IF(OR(B12="",C12=""),"",B12/C12) -> 0.27634003 | G12: =IF(OR(B12="",D12=""),"",B12/D12) -> 0.22127786 | H12: =IF(OR(B12="",E12=""),"",B12/E12) -> 0.27634003
A13: Cidão | B13: =IFERROR(VLOOKUP(A13, Lanches!$A:$C, 3, FALSE), IFERROR(VLOOKUP(A13, 'Porções'!$A:$C, 3, FALSE), IFERROR(VLOOKUP(A13, Bebidas!$A:$F, 6, FALSE), IFERROR(VLOOKUP(A13, Sobremesas!$A:$F, 3, FALSE), IFERROR(VLOOKUP(A13, Combos!$A:$F, 2, FALSE), ""))))) -> 17.067431 | C13: 59.9 | D13: 74.7 | E13: 59.9 | F13: =IF(OR(B13="",C13=""),"",B13/C13) -> 0.28493207 | G13: =IF(OR(B13="",D13=""),"",B13/D13) -> 0.22847966 | H13: =IF(OR(B13="",E13=""),"",B13/E13) -> 0.28493207
A14: Priscilo | B14: =IFERROR(VLOOKUP(A14, Lanches!$A:$C, 3, FALSE), IFERROR(VLOOKUP(A14, 'Porções'!$A:$C, 3, FALSE), IFERROR(VLOOKUP(A14, Bebidas!$A:$F, 6, FALSE), IFERROR(VLOOKUP(A14, Sobremesas!$A:$F, 3, FALSE), IFERROR(VLOOKUP(A14, Combos!$A:$F, 2, FALSE), ""))))) -> 4.9151065 | C14: 35 | D14: 41.7 | E14: 35 | F14: =IF(OR(B14="",C14=""),"",B14/C14) -> 0.14043161 | G14: =IF(OR(B14="",D14=""),"",B14/D14) -> 0.11786826 | H14: =IF(OR(B14="",E14=""),"",B14/E14) -> 0.14043161
A15: Vintão | B15: =IFERROR(VLOOKUP(A15, Lanches!$A:$C, 3, FALSE), IFERROR(VLOOKUP(A15, 'Porções'!$A:$C, 3, FALSE), IFERROR(VLOOKUP(A15, Bebidas!$A:$F, 6, FALSE), IFERROR(VLOOKUP(A15, Sobremesas!$A:$F, 3, FALSE), IFERROR(VLOOKUP(A15, Combos!$A:$F, 2, FALSE), ""))))) -> 8.1472705 | C15: 25 | D15: 30 | E15: 25 | F15: =IF(OR(B15="",C15=""),"",B15/C15) -> 0.32589082 | G15: =IF(OR(B15="",D15=""),"",B15/D15) -> 0.27157568 | H15: =IF(OR(B15="",E15=""),"",B15/E15) -> 0.32589082
A16: PORÇÕES | F16: =IF(OR($B$4="",C16=""),"",$B$4/C16) | H16: =IF(OR($B$4="",E16=""),"",$B$4/E16)
A17: Batata P | B17: =IFERROR(VLOOKUP(A17, Lanches!$A:$C, 3, FALSE), IFERROR(VLOOKUP(A17, 'Porções'!$A:$C, 3, FALSE), IFERROR(VLOOKUP(A17, Bebidas!$A:$F, 6, FALSE), IFERROR(VLOOKUP(A17, Sobremesas!$A:$F, 3, FALSE), IFERROR(VLOOKUP(A17, Combos!$A:$F, 2, FALSE), ""))))) -> 3.2723077 | C17: 20 | D17: 24.9 | E17: 20 | F17: =IF(OR(B17="",C17=""),"",B17/C17) -> 0.16361538 | G17: =IF(OR(B17="",D17=""),"",B17/D17) -> 0.13141798 | H17: =IF(OR(B17="",E17=""),"",B17/E17) -> 0.16361538
A18: Batata M | B18: =IFERROR(VLOOKUP(A18, Lanches!$A:$C, 3, FALSE), IFERROR(VLOOKUP(A18, 'Porções'!$A:$C, 3, FALSE), IFERROR(VLOOKUP(A18, Bebidas!$A:$F, 6, FALSE), IFERROR(VLOOKUP(A18, Sobremesas!$A:$F, 3, FALSE), IFERROR(VLOOKUP(A18, Combos!$A:$F, 2, FALSE), ""))))) -> 5.6246154 | C18: 25 | D18: 31.9 | E18: 25 | F18: =IF(OR(B18="",C18=""),"",B18/C18) -> 0.22498462 | G18: =IF(OR(B18="",D18=""),"",B18/D18) -> 0.17632023 | H18: =IF(OR(B18="",E18=""),"",B18/E18) -> 0.22498462
A19: Batata G | B19: =IFERROR(VLOOKUP(A19, Lanches!$A:$C, 3, FALSE), IFERROR(VLOOKUP(A19, 'Porções'!$A:$C, 3, FALSE), IFERROR(VLOOKUP(A19, Bebidas!$A:$F, 6, FALSE), IFERROR(VLOOKUP(A19, Sobremesas!$A:$F, 3, FALSE), IFERROR(VLOOKUP(A19, Combos!$A:$F, 2, FALSE), ""))))) -> 10.329231 | C19: 35 | D19: 36.9 | E19: 35 | F19: =IF(OR(B19="",C19=""),"",B19/C19) -> 0.29512088 | G19: =IF(OR(B19="",D19=""),"",B19/D19) -> 0.27992495 | H19: =IF(OR(B19="",E19=""),"",B19/E19) -> 0.29512088
A20: Onion Rings P | B20: =IFERROR(VLOOKUP(A20, Lanches!$A:$C, 3, FALSE), IFERROR(VLOOKUP(A20, 'Porções'!$A:$C, 3, FALSE), IFERROR(VLOOKUP(A20, Bebidas!$A:$F, 6, FALSE), IFERROR(VLOOKUP(A20, Sobremesas!$A:$F, 3, FALSE), IFERROR(VLOOKUP(A20, Combos!$A:$F, 2, FALSE), ""))))) -> 3.296 | C20: 20 | D20: 24.9 | E20: 20 | F20: =IF(OR(B20="",C20=""),"",B20/C20) -> 0.1648 | G20: =IF(OR(B20="",D20=""),"",B20/D20) -> 0.13236948 | H20: =IF(OR(B20="",E20=""),"",B20/E20) -> 0.1648
A21: Onion Rings M | B21: =IFERROR(VLOOKUP(A21, Lanches!$A:$C, 3, FALSE), IFERROR(VLOOKUP(A21, 'Porções'!$A:$C, 3, FALSE), IFERROR(VLOOKUP(A21, Bebidas!$A:$F, 6, FALSE), IFERROR(VLOOKUP(A21, Sobremesas!$A:$F, 3, FALSE), IFERROR(VLOOKUP(A21, Combos!$A:$F, 2, FALSE), ""))))) -> 4.484 | C21: 25 | D21: 31.9 | E21: 25 | F21: =IF(OR(B21="",C21=""),"",B21/C21) -> 0.17936 | G21: =IF(OR(B21="",D21=""),"",B21/D21) -> 0.14056426 | H21: =IF(OR(B21="",E21=""),"",B21/E21) -> 0.17936
A22: Onion Rings G | B22: =IFERROR(VLOOKUP(A22, Lanches!$A:$C, 3, FALSE), IFERROR(VLOOKUP(A22, 'Porções'!$A:$C, 3, FALSE), IFERROR(VLOOKUP(A22, Bebidas!$A:$F, 6, FALSE), IFERROR(VLOOKUP(A22, Sobremesas!$A:$F, 3, FALSE), IFERROR(VLOOKUP(A22, Combos!$A:$F, 2, FALSE), ""))))) -> 6.86 | C22: 35 | D22: 37.7 | E22: 35 | F22: =IF(OR(B22="",C22=""),"",B22/C22) -> 0.196 | G22: =IF(OR(B22="",D22=""),"",B22/D22) -> 0.18196286 | H22: =IF(OR(B22="",E22=""),"",B22/E22) -> 0.196
A23: Nuggets P | B23: =IFERROR(VLOOKUP(A23, Lanches!$A:$C, 3, FALSE), IFERROR(VLOOKUP(A23, 'Porções'!$A:$C, 3, FALSE), IFERROR(VLOOKUP(A23, Bebidas!$A:$F, 6, FALSE), IFERROR(VLOOKUP(A23, Sobremesas!$A:$F, 3, FALSE), IFERROR(VLOOKUP(A23, Combos!$A:$F, 2, FALSE), ""))))) -> 4.6317015 | C23: 20 | D23: 24.9 | E23: 20 | F23: =IF(OR(B23="",C23=""),"",B23/C23) -> 0.23158508 | G23: =IF(OR(B23="",D23=""),"",B23/D23) -> 0.18601211 | H23: =IF(OR(B23="",E23=""),"",B23/E23) -> 0.23158508
A24: Nuggets M | B24: =IFERROR(VLOOKUP(A24, Lanches!$A:$C, 3, FALSE), IFERROR(VLOOKUP(A24, 'Porções'!$A:$C, 3, FALSE), IFERROR(VLOOKUP(A24, Bebidas!$A:$F, 6, FALSE), IFERROR(VLOOKUP(A24, Sobremesas!$A:$F, 3, FALSE), IFERROR(VLOOKUP(A24, Combos!$A:$F, 2, FALSE), ""))))) -> 7.8794404 | C24: 25 | D24: 31.9 | E24: 25 | F24: =IF(OR(B24="",C24=""),"",B24/C24) -> 0.31517762 | G24: =IF(OR(B24="",D24=""),"",B24/D24) -> 0.2470044 | H24: =IF(OR(B24="",E24=""),"",B24/E24) -> 0.31517762
A25: Nuggets G | B25: =IFERROR(VLOOKUP(A25, Lanches!$A:$C, 3, FALSE), IFERROR(VLOOKUP(A25, 'Porções'!$A:$C, 3, FALSE), IFERROR(VLOOKUP(A25, Bebidas!$A:$F, 6, FALSE), IFERROR(VLOOKUP(A25, Sobremesas!$A:$F, 3, FALSE), IFERROR(VLOOKUP(A25, Combos!$A:$F, 2, FALSE), ""))))) -> 14.838881 | C25: 40 | D25: 43.7 | E25: 40 | F25: =IF(OR(B25="",C25=""),"",B25/C25) -> 0.37097202 | G25: =IF(OR(B25="",D25=""),"",B25/D25) -> 0.33956249 | H25: =IF(OR(B25="",E25=""),"",B25/E25) -> 0.37097202
A26: Batatocs Cheddar + Bacon | B26: =IFERROR(VLOOKUP(A26, Lanches!$A:$C, 3, FALSE), IFERROR(VLOOKUP(A26, 'Porções'!$A:$C, 3, FALSE), IFERROR(VLOOKUP(A26, Bebidas!$A:$F, 6, FALSE), IFERROR(VLOOKUP(A26, Sobremesas!$A:$F, 3, FALSE), IFERROR(VLOOKUP(A26, Combos!$A:$F, 2, FALSE), ""))))) -> 12.542897 | C26: 39 | D26: 49.9 | E26: 39 | F26: =IF(OR(B26="",C26=""),"",B26/C26) -> 0.32161273 | G26: =IF(OR(B26="",D26=""),"",B26/D26) -> 0.25136065 | H26: =IF(OR(B26="",E26=""),"",B26/E26) -> 0.32161273
A27: Batatocs Gorgonzola + Bacon | B27: =IFERROR(VLOOKUP(A27, Lanches!$A:$C, 3, FALSE), IFERROR(VLOOKUP(A27, 'Porções'!$A:$C, 3, FALSE), IFERROR(VLOOKUP(A27, Bebidas!$A:$F, 6, FALSE), IFERROR(VLOOKUP(A27, Sobremesas!$A:$F, 3, FALSE), IFERROR(VLOOKUP(A27, Combos!$A:$F, 2, FALSE), ""))))) -> 13.254369 | C27: 39 | E27: 39 | F27: =IF(OR(B27="",C27=""),"",B27/C27) -> 0.33985563 | G27: =IF(OR(B27="",D27=""),"",B27/D27) | H27: =IF(OR(B27="",E27=""),"",B27/E27) -> 0.33985563
A28: Porção Mista | B28: =IFERROR(VLOOKUP(A28, Lanches!$A:$C, 3, FALSE), IFERROR(VLOOKUP(A28, 'Porções'!$A:$C, 3, FALSE), IFERROR(VLOOKUP(A28, Bebidas!$A:$F, 6, FALSE), IFERROR(VLOOKUP(A28, Sobremesas!$A:$F, 3, FALSE), IFERROR(VLOOKUP(A28, Combos!$A:$F, 2, FALSE), ""))))) -> 9.3600092 | C28: 45 | D28: 55 | E28: 45 | F28: =IF(OR(B28="",C28=""),"",B28/C28) -> 0.20800021 | G28: =IF(OR(B28="",D28=""),"",B28/D28) -> 0.17018199 | H28: =IF(OR(B28="",E28=""),"",B28/E28) -> 0.20800021
A29: BEBIDAS | F29: =IF(OR($B$4="",C29=""),"",$B$4/C29) | H29: =IF(OR($B$4="",E29=""),"",$B$4/E29)
A30: Coquinha 200ml normal | B30: =IFERROR(VLOOKUP(A30, Lanches!$A:$C, 3, FALSE), IFERROR(VLOOKUP(A30, 'Porções'!$A:$C, 3, FALSE), IFERROR(VLOOKUP(A30, Bebidas!$A:$F, 6, FALSE), IFERROR(VLOOKUP(A30, Sobremesas!$A:$F, 3, FALSE), IFERROR(VLOOKUP(A30, Combos!$A:$F, 2, FALSE), ""))))) -> 1.2525 | E30: 4.5 | F30: =IF(OR(B30="",C30=""),"",B30/C30) | G30: =IF(OR(B30="",D30=""),"",B30/D30) | H30: =IF(OR(B30="",E30=""),"",B30/E30) -> 0.27833333
A31: Coquinha 200ml zero | B31: =IFERROR(VLOOKUP(A31, Lanches!$A:$C, 3, FALSE), IFERROR(VLOOKUP(A31, 'Porções'!$A:$C, 3, FALSE), IFERROR(VLOOKUP(A31, Bebidas!$A:$F, 6, FALSE), IFERROR(VLOOKUP(A31, Sobremesas!$A:$F, 3, FALSE), IFERROR(VLOOKUP(A31, Combos!$A:$F, 2, FALSE), ""))))) -> 1.2541667 | E31: 4.5 | F31: =IF(OR(B31="",C31=""),"",B31/C31) | G31: =IF(OR(B31="",D31=""),"",B31/D31) | H31: =IF(OR(B31="",E31=""),"",B31/E31) -> 0.2787037
A32: Água Sem Gás | B32: =IFERROR(VLOOKUP(A32, Lanches!$A:$C, 3, FALSE), IFERROR(VLOOKUP(A32, 'Porções'!$A:$C, 3, FALSE), IFERROR(VLOOKUP(A32, Bebidas!$A:$F, 6, FALSE), IFERROR(VLOOKUP(A32, Sobremesas!$A:$F, 3, FALSE), IFERROR(VLOOKUP(A32, Combos!$A:$F, 2, FALSE), ""))))) -> 1.0675 | C32: 5 | D32: 6 | E32: 5 | F32: =IF(OR(B32="",C32=""),"",B32/C32) -> 0.2135 | G32: =IF(OR(B32="",D32=""),"",B32/D32) -> 0.17791667 | H32: =IF(OR(B32="",E32=""),"",B32/E32) -> 0.2135
A33: Água Com Gás | B33: =IFERROR(VLOOKUP(A33, Lanches!$A:$C, 3, FALSE), IFERROR(VLOOKUP(A33, 'Porções'!$A:$C, 3, FALSE), IFERROR(VLOOKUP(A33, Bebidas!$A:$F, 6, FALSE), IFERROR(VLOOKUP(A33, Sobremesas!$A:$F, 3, FALSE), IFERROR(VLOOKUP(A33, Combos!$A:$F, 2, FALSE), ""))))) -> 1.2120238 | C33: 5 | D33: 6 | E33: 5 | F33: =IF(OR(B33="",C33=""),"",B33/C33) -> 0.24240476 | G33: =IF(OR(B33="",D33=""),"",B33/D33) -> 0.20200397 | H33: =IF(OR(B33="",E33=""),"",B33/E33) -> 0.24240476
A34: Tônica | B34: =IFERROR(VLOOKUP(A34, Lanches!$A:$C, 3, FALSE), IFERROR(VLOOKUP(A34, 'Porções'!$A:$C, 3, FALSE), IFERROR(VLOOKUP(A34, Bebidas!$A:$F, 6, FALSE), IFERROR(VLOOKUP(A34, Sobremesas!$A:$F, 3, FALSE), IFERROR(VLOOKUP(A34, Combos!$A:$F, 2, FALSE), ""))))) -> 2.5833333 | C34: 5 | E34: 5 | F34: =IF(OR(B34="",C34=""),"",B34/C34) -> 0.51666667 | G34: =IF(OR(B34="",D34=""),"",B34/D34) | H34: =IF(OR(B34="",E34=""),"",B34/E34) -> 0.51666667
A35: Tônica Zero | B35: =IFERROR(VLOOKUP(A35, Lanches!$A:$C, 3, FALSE), IFERROR(VLOOKUP(A35, 'Porções'!$A:$C, 3, FALSE), IFERROR(VLOOKUP(A35, Bebidas!$A:$F, 6, FALSE), IFERROR(VLOOKUP(A35, Sobremesas!$A:$F, 3, FALSE), IFERROR(VLOOKUP(A35, Combos!$A:$F, 2, FALSE), ""))))) -> 2.6075 | C35: 5 | E35: 5 | F35: =IF(OR(B35="",C35=""),"",B35/C35) -> 0.5215 | G35: =IF(OR(B35="",D35=""),"",B35/D35) | H35: =IF(OR(B35="",E35=""),"",B35/E35) -> 0.5215
A36: Coca KS Zero | B36: =IFERROR(VLOOKUP(A36, Lanches!$A:$C, 3, FALSE), IFERROR(VLOOKUP(A36, 'Porções'!$A:$C, 3, FALSE), IFERROR(VLOOKUP(A36, Bebidas!$A:$F, 6, FALSE), IFERROR(VLOOKUP(A36, Sobremesas!$A:$F, 3, FALSE), IFERROR(VLOOKUP(A36, Combos!$A:$F, 2, FALSE), ""))))) -> 2.35 | E36: 6 | F36: =IF(OR(B36="",C36=""),"",B36/C36) | G36: =IF(OR(B36="",D36=""),"",B36/D36) | H36: =IF(OR(B36="",E36=""),"",B36/E36) -> 0.39166667
A37: Coca KS Original | B37: =IFERROR(VLOOKUP(A37, Lanches!$A:$C, 3, FALSE), IFERROR(VLOOKUP(A37, 'Porções'!$A:$C, 3, FALSE), IFERROR(VLOOKUP(A37, Bebidas!$A:$F, 6, FALSE), IFERROR(VLOOKUP(A37, Sobremesas!$A:$F, 3, FALSE), IFERROR(VLOOKUP(A37, Combos!$A:$F, 2, FALSE), ""))))) -> 2.35 | E37: 6 | F37: =IF(OR(B37="",C37=""),"",B37/C37) | G37: =IF(OR(B37="",D37=""),"",B37/D37) | H37: =IF(OR(B37="",E37=""),"",B37/E37) -> 0.39166667
A38: Coca Zero Lata | B38: =IFERROR(VLOOKUP(A38, Lanches!$A:$C, 3, FALSE), IFERROR(VLOOKUP(A38, 'Porções'!$A:$C, 3, FALSE), IFERROR(VLOOKUP(A38, Bebidas!$A:$F, 6, FALSE), IFERROR(VLOOKUP(A38, Sobremesas!$A:$F, 3, FALSE), IFERROR(VLOOKUP(A38, Combos!$A:$F, 2, FALSE), ""))))) -> 2.5273485 | C38: 7 | D38: 9 | E38: 8 | F38: =IF(OR(B38="",C38=""),"",B38/C38) -> 0.36104978 | G38: =IF(OR(B38="",D38=""),"",B38/D38) -> 0.2808165 | H38: =IF(OR(B38="",E38=""),"",B38/E38) -> 0.31591856
A39: Coca Cola Lata | B39: =IFERROR(VLOOKUP(A39, Lanches!$A:$C, 3, FALSE), IFERROR(VLOOKUP(A39, 'Porções'!$A:$C, 3, FALSE), IFERROR(VLOOKUP(A39, Bebidas!$A:$F, 6, FALSE), IFERROR(VLOOKUP(A39, Sobremesas!$A:$F, 3, FALSE), IFERROR(VLOOKUP(A39, Combos!$A:$F, 2, FALSE), ""))))) -> 2.55375 | C39: 7 | D39: 9 | E39: 8 | F39: =IF(OR(B39="",C39=""),"",B39/C39) -> 0.36482143 | G39: =IF(OR(B39="",D39=""),"",B39/D39) -> 0.28375 | H39: =IF(OR(B39="",E39=""),"",B39/E39) -> 0.31921875
A40: Citrus Lata | B40: =IFERROR(VLOOKUP(A40, Lanches!$A:$C, 3, FALSE), IFERROR(VLOOKUP(A40, 'Porções'!$A:$C, 3, FALSE), IFERROR(VLOOKUP(A40, Bebidas!$A:$F, 6, FALSE), IFERROR(VLOOKUP(A40, Sobremesas!$A:$F, 3, FALSE), IFERROR(VLOOKUP(A40, Combos!$A:$F, 2, FALSE), ""))))) -> 2.5708333 | E40: 8 | F40: =IF(OR(B40="",C40=""),"",B40/C40) | G40: =IF(OR(B40="",D40=""),"",B40/D40) | H40: =IF(OR(B40="",E40=""),"",B40/E40) -> 0.32135417
A41: Pepsi Black Lata | B41: =IFERROR(VLOOKUP(A41, Lanches!$A:$C, 3, FALSE), IFERROR(VLOOKUP(A41, 'Porções'!$A:$C, 3, FALSE), IFERROR(VLOOKUP(A41, Bebidas!$A:$F, 6, FALSE), IFERROR(VLOOKUP(A41, Sobremesas!$A:$F, 3, FALSE), IFERROR(VLOOKUP(A41, Combos!$A:$F, 2, FALSE), ""))))) -> 2.6 | C41: 7 | E41: 8 | F41: =IF(OR(B41="",C41=""),"",B41/C41) -> 0.37142857 | G41: =IF(OR(B41="",D41=""),"",B41/D41) | H41: =IF(OR(B41="",E41=""),"",B41/E41) -> 0.325
A42: Guaraná Lata | B42: =IFERROR(VLOOKUP(A42, Lanches!$A:$C, 3, FALSE), IFERROR(VLOOKUP(A42, 'Porções'!$A:$C, 3, FALSE), IFERROR(VLOOKUP(A42, Bebidas!$A:$F, 6, FALSE), IFERROR(VLOOKUP(A42, Sobremesas!$A:$F, 3, FALSE), IFERROR(VLOOKUP(A42, Combos!$A:$F, 2, FALSE), ""))))) -> 2.6075 | C42: 7 | D42: 9 | E42: 8 | F42: =IF(OR(B42="",C42=""),"",B42/C42) -> 0.3725 | G42: =IF(OR(B42="",D42=""),"",B42/D42) -> 0.28972222 | H42: =IF(OR(B42="",E42=""),"",B42/E42) -> 0.3259375
A43: Guaraná Zero Lata | B43: =IFERROR(VLOOKUP(A43, Lanches!$A:$C, 3, FALSE), IFERROR(VLOOKUP(A43, 'Porções'!$A:$C, 3, FALSE), IFERROR(VLOOKUP(A43, Bebidas!$A:$F, 6, FALSE), IFERROR(VLOOKUP(A43, Sobremesas!$A:$F, 3, FALSE), IFERROR(VLOOKUP(A43, Combos!$A:$F, 2, FALSE), ""))))) -> 2.6075 | C43: 7 | E43: 8 | F43: =IF(OR(B43="",C43=""),"",B43/C43) -> 0.3725 | G43: =IF(OR(B43="",D43=""),"",B43/D43) | H43: =IF(OR(B43="",E43=""),"",B43/E43) -> 0.3259375
A44: Sukita Laranja Lata | B44: =IFERROR(VLOOKUP(A44, Lanches!$A:$C, 3, FALSE), IFERROR(VLOOKUP(A44, 'Porções'!$A:$C, 3, FALSE), IFERROR(VLOOKUP(A44, Bebidas!$A:$F, 6, FALSE), IFERROR(VLOOKUP(A44, Sobremesas!$A:$F, 3, FALSE), IFERROR(VLOOKUP(A44, Combos!$A:$F, 2, FALSE), ""))))) -> 2.6075 | C44: 7 | E44: 8 | F44: =IF(OR(B44="",C44=""),"",B44/C44) -> 0.3725 | G44: =IF(OR(B44="",D44=""),"",B44/D44) | H44: =IF(OR(B44="",E44=""),"",B44/E44) -> 0.3259375
A45: Coca Zero 600ml | B45: =IFERROR(VLOOKUP(A45, Lanches!$A:$C, 3, FALSE), IFERROR(VLOOKUP(A45, 'Porções'!$A:$C, 3, FALSE), IFERROR(VLOOKUP(A45, Bebidas!$A:$F, 6, FALSE), IFERROR(VLOOKUP(A45, Sobremesas!$A:$F, 3, FALSE), IFERROR(VLOOKUP(A45, Combos!$A:$F, 2, FALSE), ""))))) -> 3.3172917 | C45: 12 | D45: 12.9 | E45: 12 | F45: =IF(OR(B45="",C45=""),"",B45/C45) -> 0.27644097 | G45: =IF(OR(B45="",D45=""),"",B45/D45) -> 0.25715439 | H45: =IF(OR(B45="",E45=""),"",B45/E45) -> 0.27644097
A46: Coca Cola 600ml | B46: =IFERROR(VLOOKUP(A46, Lanches!$A:$C, 3, FALSE), IFERROR(VLOOKUP(A46, 'Porções'!$A:$C, 3, FALSE), IFERROR(VLOOKUP(A46, Bebidas!$A:$F, 6, FALSE), IFERROR(VLOOKUP(A46, Sobremesas!$A:$F, 3, FALSE), IFERROR(VLOOKUP(A46, Combos!$A:$F, 2, FALSE), ""))))) -> 3.3230556 | C46: 12 | D46: 12.9 | E46: 12 | F46: =IF(OR(B46="",C46=""),"",B46/C46) -> 0.2769213 | G46: =IF(OR(B46="",D46=""),"",B46/D46) -> 0.25760121 | H46: =IF(OR(B46="",E46=""),"",B46/E46) -> 0.2769213
A47: Guaraná 600ml | B47: =IFERROR(VLOOKUP(A47, Lanches!$A:$C, 3, FALSE), IFERROR(VLOOKUP(A47, 'Porções'!$A:$C, 3, FALSE), IFERROR(VLOOKUP(A47, Bebidas!$A:$F, 6, FALSE), IFERROR(VLOOKUP(A47, Sobremesas!$A:$F, 3, FALSE), IFERROR(VLOOKUP(A47, Combos!$A:$F, 2, FALSE), ""))))) -> 3.6666667 | C47: 12 | D47: 12.9 | E47: 12 | F47: =IF(OR(B47="",C47=""),"",B47/C47) -> 0.30555556 | G47: =IF(OR(B47="",D47=""),"",B47/D47) -> 0.28423773 | H47: =IF(OR(B47="",E47=""),"",B47/E47) -> 0.30555556
A48: Guaraná Zero 600ml | B48: =IFERROR(VLOOKUP(A48, Lanches!$A:$C, 3, FALSE), IFERROR(VLOOKUP(A48, 'Porções'!$A:$C, 3, FALSE), IFERROR(VLOOKUP(A48, Bebidas!$A:$F, 6, FALSE), IFERROR(VLOOKUP(A48, Sobremesas!$A:$F, 3, FALSE), IFERROR(VLOOKUP(A48, Combos!$A:$F, 2, FALSE), ""))))) -> 2.6075 | D48: 12.9 | E48: 12 | F48: =IF(OR(B48="",C48=""),"",B48/C48) | G48: =IF(OR(B48="",D48=""),"",B48/D48) -> 0.20213178 | H48: =IF(OR(B48="",E48=""),"",B48/E48) -> 0.21729167
A49: Suco Prats Laranja | B49: =IFERROR(VLOOKUP(A49, Lanches!$A:$C, 3, FALSE), IFERROR(VLOOKUP(A49, 'Porções'!$A:$C, 3, FALSE), IFERROR(VLOOKUP(A49, Bebidas!$A:$F, 6, FALSE), IFERROR(VLOOKUP(A49, Sobremesas!$A:$F, 3, FALSE), IFERROR(VLOOKUP(A49, Combos!$A:$F, 2, FALSE), ""))))) -> 4.5 | C49: 14 | D49: 15 | E49: 14 | F49: =IF(OR(B49="",C49=""),"",B49/C49) -> 0.32142857 | G49: =IF(OR(B49="",D49=""),"",B49/D49) -> 0.3 | H49: =IF(OR(B49="",E49=""),"",B49/E49) -> 0.32142857
A50: Suco Prats Uva | B50: =IFERROR(VLOOKUP(A50, Lanches!$A:$C, 3, FALSE), IFERROR(VLOOKUP(A50, 'Porções'!$A:$C, 3, FALSE), IFERROR(VLOOKUP(A50, Bebidas!$A:$F, 6, FALSE), IFERROR(VLOOKUP(A50, Sobremesas!$A:$F, 3, FALSE), IFERROR(VLOOKUP(A50, Combos!$A:$F, 2, FALSE), ""))))) -> 5 | C50: 14 | D50: 15 | E50: 14 | F50: =IF(OR(B50="",C50=""),"",B50/C50) -> 0.35714286 | G50: =IF(OR(B50="",D50=""),"",B50/D50) -> 0.33333333 | H50: =IF(OR(B50="",E50=""),"",B50/E50) -> 0.35714286
A51: Chopp Brahma | B51: =IFERROR(VLOOKUP(A51, Lanches!$A:$C, 3, FALSE), IFERROR(VLOOKUP(A51, 'Porções'!$A:$C, 3, FALSE), IFERROR(VLOOKUP(A51, Bebidas!$A:$F, 6, FALSE), IFERROR(VLOOKUP(A51, Sobremesas!$A:$F, 3, FALSE), IFERROR(VLOOKUP(A51, Combos!$A:$F, 2, FALSE), ""))))) -> 0.05 | E51: 14 | F51: =IF(OR(B51="",C51=""),"",B51/C51) | G51: =IF(OR(B51="",D51=""),"",B51/D51) | H51: =IF(OR(B51="",E51=""),"",B51/E51) -> 0.0035714286
A52: Coca Cola 1L | B52: =IFERROR(VLOOKUP(A52, Lanches!$A:$C, 3, FALSE), IFERROR(VLOOKUP(A52, 'Porções'!$A:$C, 3, FALSE), IFERROR(VLOOKUP(A52, Bebidas!$A:$F, 6, FALSE), IFERROR(VLOOKUP(A52, Sobremesas!$A:$F, 3, FALSE), IFERROR(VLOOKUP(A52, Combos!$A:$F, 2, FALSE), ""))))) -> 5.8008333 | E52: 15 | F52: =IF(OR(B52="",C52=""),"",B52/C52) | G52: =IF(OR(B52="",D52=""),"",B52/D52) | H52: =IF(OR(B52="",E52=""),"",B52/E52) -> 0.38672222
A53: Cerveja Original 600ml | B53: =IFERROR(VLOOKUP(A53, Lanches!$A:$C, 3, FALSE), IFERROR(VLOOKUP(A53, 'Porções'!$A:$C, 3, FALSE), IFERROR(VLOOKUP(A53, Bebidas!$A:$F, 6, FALSE), IFERROR(VLOOKUP(A53, Sobremesas!$A:$F, 3, FALSE), IFERROR(VLOOKUP(A53, Combos!$A:$F, 2, FALSE), ""))))) -> 7.3233333 | E53: 16 | F53: =IF(OR(B53="",C53=""),"",B53/C53) | G53: =IF(OR(B53="",D53=""),"",B53/D53) | H53: =IF(OR(B53="",E53=""),"",B53/E53) -> 0.45770833
A54: Coca Zero 2L | B54: =IFERROR(VLOOKUP(A54, Lanches!$A:$C, 3, FALSE), IFERROR(VLOOKUP(A54, 'Porções'!$A:$C, 3, FALSE), IFERROR(VLOOKUP(A54, Bebidas!$A:$F, 6, FALSE), IFERROR(VLOOKUP(A54, Sobremesas!$A:$F, 3, FALSE), IFERROR(VLOOKUP(A54, Combos!$A:$F, 2, FALSE), ""))))) -> 8.16 | C54: 20 | D54: 22 | E54: 20 | F54: =IF(OR(B54="",C54=""),"",B54/C54) -> 0.408 | G54: =IF(OR(B54="",D54=""),"",B54/D54) -> 0.37090909 | H54: =IF(OR(B54="",E54=""),"",B54/E54) -> 0.408
A55: Coca Cola 2L | B55: =IFERROR(VLOOKUP(A55, Lanches!$A:$C, 3, FALSE), IFERROR(VLOOKUP(A55, 'Porções'!$A:$C, 3, FALSE), IFERROR(VLOOKUP(A55, Bebidas!$A:$F, 6, FALSE), IFERROR(VLOOKUP(A55, Sobremesas!$A:$F, 3, FALSE), IFERROR(VLOOKUP(A55, Combos!$A:$F, 2, FALSE), ""))))) -> 8.1672 | C55: 20 | D55: 22 | E55: 20 | F55: =IF(OR(B55="",C55=""),"",B55/C55) -> 0.40836 | G55: =IF(OR(B55="",D55=""),"",B55/D55) -> 0.37123636 | H55: =IF(OR(B55="",E55=""),"",B55/E55) -> 0.40836
A56: SOBREMESAS | F56: =IF(OR($B$4="",C56=""),"",$B$4/C56) | H56: =IF(OR($B$4="",E56=""),"",$B$4/E56)
A57: Churros com Sorvete | B57: =IFERROR(VLOOKUP(A57, Lanches!$A:$C, 3, FALSE), IFERROR(VLOOKUP(A57, 'Porções'!$A:$C, 3, FALSE), IFERROR(VLOOKUP(A57, Bebidas!$A:$F, 6, FALSE), IFERROR(VLOOKUP(A57, Sobremesas!$A:$F, 3, FALSE), IFERROR(VLOOKUP(A57, Combos!$A:$F, 2, FALSE), ""))))) -> 10.62 | E57: 32 | F57: =IF(OR(B57="",C57=""),"",B57/C57) | G57: =IF(OR(B57="",D57=""),"",B57/D57) | H57: =IF(OR(B57="",E57=""),"",B57/E57) -> 0.331875
A58: Churros Especial | B58: =IFERROR(VLOOKUP(A58, Lanches!$A:$C, 3, FALSE), IFERROR(VLOOKUP(A58, 'Porções'!$A:$C, 3, FALSE), IFERROR(VLOOKUP(A58, Bebidas!$A:$F, 6, FALSE), IFERROR(VLOOKUP(A58, Sobremesas!$A:$F, 3, FALSE), IFERROR(VLOOKUP(A58, Combos!$A:$F, 2, FALSE), ""))))) -> 7.0956 | E58: 32 | F58: =IF(OR(B58="",C58=""),"",B58/C58) | G58: =IF(OR(B58="",D58=""),"",B58/D58) | H58: =IF(OR(B58="",E58=""),"",B58/E58) -> 0.2217375
A59: Brownie com Sorvete | B59: =IFERROR(VLOOKUP(A59, Lanches!$A:$C, 3, FALSE), IFERROR(VLOOKUP(A59, 'Porções'!$A:$C, 3, FALSE), IFERROR(VLOOKUP(A59, Bebidas!$A:$F, 6, FALSE), IFERROR(VLOOKUP(A59, Sobremesas!$A:$F, 3, FALSE), IFERROR(VLOOKUP(A59, Combos!$A:$F, 2, FALSE), ""))))) -> 13.22 | E59: 32 | F59: =IF(OR(B59="",C59=""),"",B59/C59) | G59: =IF(OR(B59="",D59=""),"",B59/D59) | H59: =IF(OR(B59="",E59=""),"",B59/E59) -> 0.413125
A60: Copo de Sorvete | B60: =IFERROR(VLOOKUP(A60, Lanches!$A:$C, 3, FALSE), IFERROR(VLOOKUP(A60, 'Porções'!$A:$C, 3, FALSE), IFERROR(VLOOKUP(A60, Bebidas!$A:$F, 6, FALSE), IFERROR(VLOOKUP(A60, Sobremesas!$A:$F, 3, FALSE), IFERROR(VLOOKUP(A60, Combos!$A:$F, 2, FALSE), ""))))) -> 14.7378 | E60: 25 | F60: =IF(OR(B60="",C60=""),"",B60/C60) | G60: =IF(OR(B60="",D60=""),"",B60/D60) | H60: =IF(OR(B60="",E60=""),"",B60/E60) -> 0.589512
A61: Churros do And | B61: =IFERROR(VLOOKUP(A61, Lanches!$A:$C, 3, FALSE), IFERROR(VLOOKUP(A61, 'Porções'!$A:$C, 3, FALSE), IFERROR(VLOOKUP(A61, Bebidas!$A:$F, 6, FALSE), IFERROR(VLOOKUP(A61, Sobremesas!$A:$F, 3, FALSE), IFERROR(VLOOKUP(A61, Combos!$A:$F, 2, FALSE), ""))))) -> 4.76 | C61: 20 | D61: 25 | F61: =IF(OR(B61="",C61=""),"",B61/C61) -> 0.238 | G61: =IF(OR(B61="",D61=""),"",B61/D61) -> 0.1904 | H61: =IF(OR(B61="",E61=""),"",B61/E61)
A62: Cookie Red Velvet Lhamaria | B62: =IFERROR(VLOOKUP(A62, Lanches!$A:$C, 3, FALSE), IFERROR(VLOOKUP(A62, 'Porções'!$A:$C, 3, FALSE), IFERROR(VLOOKUP(A62, Bebidas!$A:$F, 6, FALSE), IFERROR(VLOOKUP(A62, Sobremesas!$A:$F, 3, FALSE), IFERROR(VLOOKUP(A62, Combos!$A:$F, 2, FALSE), ""))))) -> 6.5 | C62: 14 | D62: 16 | E62: 14 | F62: =IF(OR(B62="",C62=""),"",B62/C62) -> 0.46428571 | G62: =IF(OR(B62="",D62=""),"",B62/D62) -> 0.40625 | H62: =IF(OR(B62="",E62=""),"",B62/E62) -> 0.46428571
A63: Brownie de Chocolate Lhamaria | B63: =IFERROR(VLOOKUP(A63, Lanches!$A:$C, 3, FALSE), IFERROR(VLOOKUP(A63, 'Porções'!$A:$C, 3, FALSE), IFERROR(VLOOKUP(A63, Bebidas!$A:$F, 6, FALSE), IFERROR(VLOOKUP(A63, Sobremesas!$A:$F, 3, FALSE), IFERROR(VLOOKUP(A63, Combos!$A:$F, 2, FALSE), ""))))) -> 6.5 | D63: 16 | E63: 14 | F63: =IF(OR(B63="",C63=""),"",B63/C63) | G63: =IF(OR(B63="",D63=""),"",B63/D63) -> 0.40625 | H63: =IF(OR(B63="",E63=""),"",B63/E63) -> 0.46428571
A64: COMBOS
A65: Combo Kids | B65: =IFERROR(VLOOKUP(A65, Lanches!$A:$C, 3, FALSE), IFERROR(VLOOKUP(A65, 'Porções'!$A:$C, 3, FALSE), IFERROR(VLOOKUP(A65, Bebidas!$A:$F, 6, FALSE), IFERROR(VLOOKUP(A65, Sobremesas!$A:$F, 3, FALSE), IFERROR(VLOOKUP(A65, Combos!$A:$F, 2, FALSE), ""))))) -> 7.8860182 | C65: 35.5 | E65: 39 | F65: =IF(OR(B65="",C65=""),"",B65/C65) -> 0.22214136 | G65: =IF(OR(B65="",D65=""),"",B65/D65) | H65: =IF(OR(B65="",E65=""),"",B65/E65) -> 0.20220559
A66: Combão Priscilo | B66: =IFERROR(VLOOKUP(A66, Lanches!$A:$C, 3, FALSE), IFERROR(VLOOKUP(A66, 'Porções'!$A:$C, 3, FALSE), IFERROR(VLOOKUP(A66, Bebidas!$A:$F, 6, FALSE), IFERROR(VLOOKUP(A66, Sobremesas!$A:$F, 3, FALSE), IFERROR(VLOOKUP(A66, Combos!$A:$F, 2, FALSE), ""))))) -> 8.1874142 | C66: 55 | F66: =IF(OR(B66="",C66=""),"",B66/C66) -> 0.14886208 | G66: =IF(OR(B66="",D66=""),"",B66/D66) | H66: =IF(OR(B66="",E66=""),"",B66/E66)
A67: Combão Cidão | B67: =IFERROR(VLOOKUP(A67, Lanches!$A:$C, 3, FALSE), IFERROR(VLOOKUP(A67, 'Porções'!$A:$C, 3, FALSE), IFERROR(VLOOKUP(A67, Bebidas!$A:$F, 6, FALSE), IFERROR(VLOOKUP(A67, Sobremesas!$A:$F, 3, FALSE), IFERROR(VLOOKUP(A67, Combos!$A:$F, 2, FALSE), ""))))) -> 20.339739 | C67: 79.9 | D67: 101.7 | E67: 78 | F67: =IF(OR(B67="",C67=""),"",B67/C67) -> 0.25456494 | G67: =IF(OR(B67="",D67=""),"",B67/D67) -> 0.19999743 | H67: =IF(OR(B67="",E67=""),"",B67/E67) -> 0.26076588
A68: Combão Mussarelo | B68: =IFERROR(VLOOKUP(A68, Lanches!$A:$C, 3, FALSE), IFERROR(VLOOKUP(A68, 'Porções'!$A:$C, 3, FALSE), IFERROR(VLOOKUP(A68, Bebidas!$A:$F, 6, FALSE), IFERROR(VLOOKUP(A68, Sobremesas!$A:$F, 3, FALSE), IFERROR(VLOOKUP(A68, Combos!$A:$F, 2, FALSE), ""))))) -> 15.154929 | C68: 63 | D68: 80.7 | E68: 63 | F68: =IF(OR(B68="",C68=""),"",B68/C68) -> 0.24055443 | G68: =IF(OR(B68="",D68=""),"",B68/D68) -> 0.18779342 | H68: =IF(OR(B68="",E68=""),"",B68/E68) -> 0.24055443
A69: Combão Osvaldão | B69: =IFERROR(VLOOKUP(A69, Lanches!$A:$C, 3, FALSE), IFERROR(VLOOKUP(A69, 'Porções'!$A:$C, 3, FALSE), IFERROR(VLOOKUP(A69, Bebidas!$A:$F, 6, FALSE), IFERROR(VLOOKUP(A69, Sobremesas!$A:$F, 3, FALSE), IFERROR(VLOOKUP(A69, Combos!$A:$F, 2, FALSE), ""))))) -> 14.669364 | C69: 59 | D69: 78.9 | E69: 59 | F69: =IF(OR(B69="",C69=""),"",B69/C69) -> 0.24863328 | G69: =IF(OR(B69="",D69=""),"",B69/D69) -> 0.18592349 | H69: =IF(OR(B69="",E69=""),"",B69/E69) -> 0.24863328
A70: Combão DBS | B70: =IFERROR(VLOOKUP(A70, Lanches!$A:$C, 3, FALSE), IFERROR(VLOOKUP(A70, 'Porções'!$A:$C, 3, FALSE), IFERROR(VLOOKUP(A70, Bebidas!$A:$F, 6, FALSE), IFERROR(VLOOKUP(A70, Sobremesas!$A:$F, 3, FALSE), IFERROR(VLOOKUP(A70, Combos!$A:$F, 2, FALSE), ""))))) -> 14.324984 | C70: 58 | D70: 88 | E70: 58 | F70: =IF(OR(B70="",C70=""),"",B70/C70) -> 0.24698248 | G70: =IF(OR(B70="",D70=""),"",B70/D70) -> 0.1627839 | H70: =IF(OR(B70="",E70=""),"",B70/E70) -> 0.24698248
A71: Combo Vintão | B71: =IFERROR(VLOOKUP(A71, Lanches!$A:$C, 3, FALSE), IFERROR(VLOOKUP(A71, 'Porções'!$A:$C, 3, FALSE), IFERROR(VLOOKUP(A71, Bebidas!$A:$F, 6, FALSE), IFERROR(VLOOKUP(A71, Sobremesas!$A:$F, 3, FALSE), IFERROR(VLOOKUP(A71, Combos!$A:$F, 2, FALSE), ""))))) -> 11.419578 | E71: 45 | F71: =IF(OR(B71="",C71=""),"",B71/C71) | G71: =IF(OR(B71="",D71=""),"",B71/D71) | H71: =IF(OR(B71="",E71=""),"",B71/E71) -> 0.2537684
A72: Combão Beicão | B72: =IFERROR(VLOOKUP(A72, Lanches!$A:$C, 3, FALSE), IFERROR(VLOOKUP(A72, 'Porções'!$A:$C, 3, FALSE), IFERROR(VLOOKUP(A72, Bebidas!$A:$F, 6, FALSE), IFERROR(VLOOKUP(A72, Sobremesas!$A:$F, 3, FALSE), IFERROR(VLOOKUP(A72, Combos!$A:$F, 2, FALSE), ""))))) -> 15.797544 | C72: 59 | D72: 86.9 | E72: 59 | F72: =IF(OR(B72="",C72=""),"",B72/C72) -> 0.26775498 | G72: =IF(OR(B72="",D72=""),"",B72/D72) -> 0.18178991 | H72: =IF(OR(B72="",E72=""),"",B72/E72) -> 0.26775498
A73: Combão Galactos | B73: =IFERROR(VLOOKUP(A73, Lanches!$A:$C, 3, FALSE), IFERROR(VLOOKUP(A73, 'Porções'!$A:$C, 3, FALSE), IFERROR(VLOOKUP(A73, Bebidas!$A:$F, 6, FALSE), IFERROR(VLOOKUP(A73, Sobremesas!$A:$F, 3, FALSE), IFERROR(VLOOKUP(A73, Combos!$A:$F, 2, FALSE), ""))))) -> 15.249394 | C73: 63 | D73: 78.9 | E73: 63 | F73: =IF(OR(B73="",C73=""),"",B73/C73) -> 0.24205387 | G73: =IF(OR(B73="",D73=""),"",B73/D73) -> 0.19327495 | H73: =IF(OR(B73="",E73=""),"",B73/E73) -> 0.24205387
A74: Combão Albieri | B74: =IFERROR(VLOOKUP(A74, Lanches!$A:$C, 3, FALSE), IFERROR(VLOOKUP(A74, 'Porções'!$A:$C, 3, FALSE), IFERROR(VLOOKUP(A74, Bebidas!$A:$F, 6, FALSE), IFERROR(VLOOKUP(A74, Sobremesas!$A:$F, 3, FALSE), IFERROR(VLOOKUP(A74, Combos!$A:$F, 2, FALSE), ""))))) -> 12.217578 | C74: 63 | D74: 78.9 | E74: 63 | F74: =IF(OR(B74="",C74=""),"",B74/C74) -> 0.1939298 | G74: =IF(OR(B74="",D74=""),"",B74/D74) -> 0.15484889 | H74: =IF(OR(B74="",E74=""),"",B74/E74) -> 0.1939298
A75: ADICIONAIS
A76: Salada | B76: =IFERROR(VLOOKUP(A76, Lanches!$A:$C, 3, FALSE), IFERROR(VLOOKUP(A76, 'Porções'!$A:$C, 3, FALSE), IFERROR(VLOOKUP(A76, Bebidas!$A:$F, 6, FALSE), IFERROR(VLOOKUP(A76, Sobremesas!$A:$F, 3, FALSE), IFERROR(VLOOKUP(A76, Combos!$A:$F, 2, FALSE), IFERROR(VLOOKUP(A76, Preparos!$A:$F, 4, FALSE), "")))))) -> 1.0305 | C76: 4 | D76: 6 | E76: 4 | F76: =IF(OR(B76="",C76=""),"",B76/C76) -> 0.257625 | G76: =IF(OR(B76="",D76=""),"",B76/D76) -> 0.17175 | H76: =IF(OR(B76="",E76=""),"",B76/E76) -> 0.257625
A77: Picles | B77: =IFERROR(VLOOKUP(A77, Lanches!$A:$C, 3, FALSE), IFERROR(VLOOKUP(A77, 'Porções'!$A:$C, 3, FALSE), IFERROR(VLOOKUP(A77, Bebidas!$A:$F, 6, FALSE), IFERROR(VLOOKUP(A77, Sobremesas!$A:$F, 3, FALSE), IFERROR(VLOOKUP(A77, Combos!$A:$F, 2, FALSE), IFERROR(VLOOKUP(A77, Preparos!$A:$F, 4, FALSE), "")))))) -> 1.144375 | C77: 4 | D77: 5 | E77: 4 | F77: =IF(OR(B77="",C77=""),"",B77/C77) -> 0.28609375 | G77: =IF(OR(B77="",D77=""),"",B77/D77) -> 0.228875 | H77: =IF(OR(B77="",E77=""),"",B77/E77) -> 0.28609375
A78: Bacon | B78: =IFERROR(VLOOKUP(A78, Lanches!$A:$C, 3, FALSE), IFERROR(VLOOKUP(A78, 'Porções'!$A:$C, 3, FALSE), IFERROR(VLOOKUP(A78, Bebidas!$A:$F, 6, FALSE), IFERROR(VLOOKUP(A78, Sobremesas!$A:$F, 3, FALSE), IFERROR(VLOOKUP(A78, Combos!$A:$F, 2, FALSE), IFERROR(VLOOKUP(A78, Preparos!$A:$F, 4, FALSE), "")))))) -> 2.9054054 | C78: 6 | D78: 9 | E78: 6 | F78: =IF(OR(B78="",C78=""),"",B78/C78) -> 0.48423423 | G78: =IF(OR(B78="",D78=""),"",B78/D78) -> 0.32282282 | H78: =IF(OR(B78="",E78=""),"",B78/E78) -> 0.48423423
A79: Onion Rings | B79: =IFERROR(VLOOKUP(A79, Lanches!$A:$C, 3, FALSE), IFERROR(VLOOKUP(A79, 'Porções'!$A:$C, 3, FALSE), IFERROR(VLOOKUP(A79, Bebidas!$A:$F, 6, FALSE), IFERROR(VLOOKUP(A79, Sobremesas!$A:$F, 3, FALSE), IFERROR(VLOOKUP(A79, Combos!$A:$F, 2, FALSE), IFERROR(VLOOKUP(A79, Preparos!$A:$F, 4, FALSE), "")))))) -> 1.188 | C79: 7 | D79: 9 | E79: 7 | F79: =IF(OR(B79="",C79=""),"",B79/C79) -> 0.16971429 | G79: =IF(OR(B79="",D79=""),"",B79/D79) -> 0.132 | H79: =IF(OR(B79="",E79=""),"",B79/E79) -> 0.16971429
A80: Creme de Gorgonzola | B80: =IFERROR(VLOOKUP(A80, Lanches!$A:$C, 3, FALSE), IFERROR(VLOOKUP(A80, 'Porções'!$A:$C, 3, FALSE), IFERROR(VLOOKUP(A80, Bebidas!$A:$F, 6, FALSE), IFERROR(VLOOKUP(A80, Sobremesas!$A:$F, 3, FALSE), IFERROR(VLOOKUP(A80, Combos!$A:$F, 2, FALSE), IFERROR(VLOOKUP(A80, Preparos!$A:$F, 4, FALSE), "")))))) -> 3.271646 | C80: 6 | D80: 8 | E80: 6 | F80: =IF(OR(B80="",C80=""),"",B80/C80) -> 0.54527433 | G80: =IF(OR(B80="",D80=""),"",B80/D80) -> 0.40895575 | H80: =IF(OR(B80="",E80=""),"",B80/E80) -> 0.54527433
A81: Cheddar | B81: =IFERROR(VLOOKUP(A81, Lanches!$A:$C, 3, FALSE), IFERROR(VLOOKUP(A81, 'Porções'!$A:$C, 3, FALSE), IFERROR(VLOOKUP(A81, Bebidas!$A:$F, 6, FALSE), IFERROR(VLOOKUP(A81, Sobremesas!$A:$F, 3, FALSE), IFERROR(VLOOKUP(A81, Combos!$A:$F, 2, FALSE), IFERROR(VLOOKUP(A81, Preparos!$A:$F, 4, FALSE), "")))))) -> 1.00772 | C81: 5 | D81: 6 | E81: 5 | F81: =IF(OR(B81="",C81=""),"",B81/C81) -> 0.201544 | G81: =IF(OR(B81="",D81=""),"",B81/D81) -> 0.16795333 | H81: =IF(OR(B81="",E81=""),"",B81/E81) -> 0.201544
A82: Mussarela | B82: =IFERROR(VLOOKUP(A82, Lanches!$A:$C, 3, FALSE), IFERROR(VLOOKUP(A82, 'Porções'!$A:$C, 3, FALSE), IFERROR(VLOOKUP(A82, Bebidas!$A:$F, 6, FALSE), IFERROR(VLOOKUP(A82, Sobremesas!$A:$F, 3, FALSE), IFERROR(VLOOKUP(A82, Combos!$A:$F, 2, FALSE), IFERROR(VLOOKUP(A82, Preparos!$A:$F, 4, FALSE), "")))))) -> 1.3596 | C82: 5 | D82: 6 | E82: 5 | F82: =IF(OR(B82="",C82=""),"",B82/C82) -> 0.27192 | G82: =IF(OR(B82="",D82=""),"",B82/D82) -> 0.2266 | H82: =IF(OR(B82="",E82=""),"",B82/E82) -> 0.27192
A83: Cebola Caramelizada Porção | B83: =IFERROR(VLOOKUP(A83, Lanches!$A:$C, 3, FALSE), IFERROR(VLOOKUP(A83, 'Porções'!$A:$C, 3, FALSE), IFERROR(VLOOKUP(A83, Bebidas!$A:$F, 6, FALSE), IFERROR(VLOOKUP(A83, Sobremesas!$A:$F, 3, FALSE), IFERROR(VLOOKUP(A83, Combos!$A:$F, 2, FALSE), IFERROR(VLOOKUP(A83, Preparos!$A:$F, 4, FALSE), "")))))) -> 0.50084535 | C83: 6 | D83: 8 | E83: 6 | F83: =IF(OR(B83="",C83=""),"",B83/C83) -> 0.083474225 | G83: =IF(OR(B83="",D83=""),"",B83/D83) -> 0.062605669 | H83: =IF(OR(B83="",E83=""),"",B83/E83) -> 0.083474225
A84: PROMOÇÕES CONSULTOR DE LUCRO
A85: COMBO ALBIERI + DBS | B85: =IFERROR(VLOOKUP(A85, Lanches!$A:$C, 3, FALSE), IFERROR(VLOOKUP(A85, 'Porções'!$A:$C, 3, FALSE), IFERROR(VLOOKUP(A85, Bebidas!$A:$F, 6, FALSE), IFERROR(VLOOKUP(A85, Sobremesas!$A:$F, 3, FALSE), IFERROR(VLOOKUP(A85, Combos!$A:$F, 2, FALSE), IFERROR(VLOOKUP(A85, Preparos!$A:$F, 4, FALSE), "")))))) -> 19.997946 | C85: 52.99 | F85: =IF(OR(B85="",C85=""),"",B85/C85) -> 0.37739094 | G85: =IF(OR(B85="",D85=""),"",B85/D85) | H85: =IF(OR(B85="",E85=""),"",B85/E85)
A86: OSVALDÃO + SIMPLES | B86: =IFERROR(VLOOKUP(A86, Lanches!$A:$C, 3, FALSE), IFERROR(VLOOKUP(A86, 'Porções'!$A:$C, 3, FALSE), IFERROR(VLOOKUP(A86, Bebidas!$A:$F, 6, FALSE), IFERROR(VLOOKUP(A86, Sobremesas!$A:$F, 3, FALSE), IFERROR(VLOOKUP(A86, Combos!$A:$F, 2, FALSE), IFERROR(VLOOKUP(A86, Preparos!$A:$F, 4, FALSE), "")))))) -> 16.010766 | C86: 48.99 | F86: =IF(OR(B86="",C86=""),"",B86/C86) -> 0.32681703 | G86: =IF(OR(B86="",D86=""),"",B86/D86) | H86: =IF(OR(B86="",E86=""),"",B86/E86)
A87: GALACTOCS + DUPLO | B87: =IFERROR(VLOOKUP(A87, Lanches!$A:$C, 3, FALSE), IFERROR(VLOOKUP(A87, 'Porções'!$A:$C, 3, FALSE), IFERROR(VLOOKUP(A87, Bebidas!$A:$F, 6, FALSE), IFERROR(VLOOKUP(A87, Sobremesas!$A:$F, 3, FALSE), IFERROR(VLOOKUP(A87, Combos!$A:$F, 2, FALSE), IFERROR(VLOOKUP(A87, Preparos!$A:$F, 4, FALSE), "")))))) -> 19.093857 | C87: 55.99 | F87: =IF(OR(B87="",C87=""),"",B87/C87) -> 0.34102262 | G87: =IF(OR(B87="",D87=""),"",B87/D87) | H87: =IF(OR(B87="",E87=""),"",B87/E87)
A88: MUSSARELO + GALACTOCS + OSVALDAO | B88: =IFERROR(VLOOKUP(A88, Lanches!$A:$C, 3, FALSE), IFERROR(VLOOKUP(A88, 'Porções'!$A:$C, 3, FALSE), IFERROR(VLOOKUP(A88, Bebidas!$A:$F, 6, FALSE), IFERROR(VLOOKUP(A88, Sobremesas!$A:$F, 3, FALSE), IFERROR(VLOOKUP(A88, Combos!$A:$F, 2, FALSE), IFERROR(VLOOKUP(A88, Preparos!$A:$F, 4, FALSE), "")))))) -> 35.256763 | C88: 91.99 | F88: =IF(OR(B88="",C88=""),"",B88/C88) -> 0.38326735 | G88: =IF(OR(B88="",D88=""),"",B88/D88) | H88: =IF(OR(B88="",E88=""),"",B88/E88)
F89: =IF(OR(B89="",C89=""),"",B89/C89) | G89: =IF(OR(B89="",D89=""),"",B89/D89) | H89: =IF(OR(B89="",E89=""),"",B89/E89)
F90: =IF(OR(B90="",C90=""),"",B90/C90) | G90: =IF(OR(B90="",D90=""),"",B90/D90) | H90: =IF(OR(B90="",E90=""),"",B90/E90)
F91: =IF(OR(B91="",C91=""),"",B91/C91) | G91: =IF(OR(B91="",D91=""),"",B91/D91) | H91: =IF(OR(B91="",E91=""),"",B91/E91)
F92: =IF(OR(B92="",C92=""),"",B92/C92) | G92: =IF(OR(B92="",D92=""),"",B92/D92) | H92: =IF(OR(B92="",E92=""),"",B92/E92)
H93: =IF(OR($B$4="",E93=""),"",$B$4/E93)
H94: =IF(OR($B$4="",E94=""),"",$B$4/E94)
H95: =IF(OR($B$4="",E95=""),"",$B$4/E95)
H96: =IF(OR($B$4="",E96=""),"",$B$4/E96)
H97: =IF(OR($B$4="",E97=""),"",$B$4/E97)
H98: =IF(OR($B$4="",E98=""),"",$B$4/E98)
H99: =IF(OR($B$4="",E99=""),"",$B$4/E99)
H100: =IF(OR($B$4="",E100=""),"",$B$4/E100)
H101: =IF(OR($B$4="",E101=""),"",$B$4/E101)
...

Sheet LISTAS
A1: Produtos_Lanches | B1: Produtos_Porções | C1: Produtos_Bebidas | D1: Produtos_Sobremesas | E1: Produtos_Combos | G1: Todos_Produtos | I1: Categorias
A2: Simples | B2: Batata P | C2: Trident Menta Envelope 8g CX21 | D2: Churros com Sorvete | E2: Combo Kids | G2: Albieri | I2: Lanche
A3: Duplo | B3: Batata M | C3: Coquinha 200ml normal | D3: Churros Especial | E3: Batata P | G3: Batata G | I3: Porção
A4: Triplo | B4: Batata G | C4: Coquinha 200ml zero | D4: Brownie com Sorvete | E4: Simples | G4: Batata M | I4: Bebida
A5: DBS | B5: Onion Rings P | C5: Água Sem Gás | D5: Copo de Sorvete | E5: Coquinha 200ml normal | G5: Batata P | I5: Sobremesa
A6: Beicão | B6: Onion Rings M | C6: Água Com Gás | D6: Churros do And | E6: Combão Priscilo | G6: Batatocs Cheddar + Bacon | I6: Combo
A7: Albieri | B7: Onion Rings G | C7: Tônica | D7: Cookie Red Velvet Lhamaria | E7: Priscilo | G7: Batatocs Gorgonzola + Bacon | I7: Adicionais
A8: Osvaldão | B8: Nuggets P | C8: Tônica Zero | D8: Brownie de Chocolate Lhamaria | E8: Batata P | G8: Beicão
A9: Galactocs | B9: Nuggets M | C9: Coca KS Zero | E9: Coca Cola Lata | G9: Brownie com Sorvete
A10: Mussarelo | B10: Nuggets G | C10: Coca KS Original | E10: Combão Cidão | G10: Brownie de Chocolate Lhamaria
A11: Cidão | B11: Batatocs Cheddar + Bacon | C11: Coca Zero Lata | E11: Cidão | G11: Cerveja Original 600ml
A12: Priscilo | B12: Batatocs Gorgonzola + Bacon | C12: Coca Cola Lata | E12: Batata P | G12: Chopp Brahma
A13: Vintão | B13: Porção Mista | C13: Citrus Lata | E13: Coca Cola Lata | G13: Churros Especial
C14: Pepsi Black Lata | E14: Combão Mussarelo | G14: Churros com Sorvete
C15: Guaraná Lata | E15: Mussarelo | G15: Churros do And
C16: Guaraná Zero Lata | E16: Batata P | G16: Cidão
C17: Sukita Laranja Lata | E17: Coca Cola Lata | G17: Citrus Lata
C18: Coca Zero 600ml | E18: Combão Osvaldão | G18: Coca Cola 1L
C19: Coca Cola 600ml | E19: Osvaldão | G19: Coca Cola 2L
C20: Guaraná 600ml | E20: Batata P | G20: Coca Cola 600ml
C21: Guaraná Zero 600ml | E21: Coca Cola Lata | G21: Coca Cola Lata
C22: Suco Prats Laranja | E22: Combão DBS | G22: Coca KS Original
C23: Suco Prats Uva | E23: DBS | G23: Coca KS Zero
C24: Chopp Brahma | E24: Batata P | G24: Coca Zero 2L
C25: Coca Cola 1L | E25: Coca Cola Lata | G25: Coca Zero 600ml
... C28: Coca Cola 2L | E28: Batata P | G28: Combo Vintão
E29: Coca Cola Lata | G29: Combão Albieri
E30: Combão Beicão | G30: Combão Beicão
E31: Beicão | G31: Combão Cidão
E32: Batata P | G32: Combão DBS
E33: Coca Cola Lata | G33: Combão Galactos
E34: Combão Galactos | G34: Combão Mussarelo
E35: Galactocs | G35: Combão Osvaldão
E36: Batata P | G36: Combão Priscilo
E37: Coca Cola Lata | G37: Cookie Red Velvet Lhamaria
E38: Combão Albieri | G38: Copo de Sorvete
E39: Albieri | G39: Coquinha 200ml normal
E40: Batata P | G40: Coquinha 200ml zero
E41: Coca Cola Lata | G41: DBS
G42: Duplo
G43: Galactocs
G44: Guaraná 600ml
G45: Guaraná Lata
G46: Guaraná Zero 600ml
G47: Guaraná Zero Lata
G48: Mussarelo
G49: Nuggets G
G50: Nuggets M
G51: Nuggets P
G52: Onion Rings G
G53: Onion Rings M
... G69: Água Sem Gás
